Workbook

Sheet Guide
A1: Trading & Investment Journal — Workbook Guide (Procedures)
A3: CONVENTIONS
B4: BLUE cells = you type. BLACK cells = calculated, do not edit. GREEN cells (Reconciliation) = links to other sheets. YELLOW = editable slot headers / key assumptions.
B5: Dates: enter as YYYY-MM-DD. Keep ONE decision per date (the app orders by timestamp; this workbook splits before/after by date).
B6: The workbook ships with the app demo data so every formula is visibly working and reconciles against the app. To start fresh: clear the blue data rows on Decisions, Trades, CashEvents and Snapshots (keep headers), then set Settings and Prices to your own.
A7: P1 — ONE-TIME SETUP
A8: 1 | B8: Open Settings: enter Starting cash (cash at inception), Benchmark ticker (SPY recommended) and Risk-free rate (used by Sharpe).
A9: 2 | B9: Open Prices: one row per ticker you own or track — current price, sector, type (stock/etf). The benchmark needs a row too.
A10: 3 | B10: Already own holdings? Add one "Buy" row per holding on Trades (date bought or today, price = your average cost), all under one Decision ID (e.g. D-000), plus a matching "Opening portfolio" row on Decisions. This mirrors the app's "Set up your portfolio" — its ghost value equals starting cash, so it reads "your holdings vs staying in cash".
A11: P2 — RECORD A DECISION (the core loop)
A12: 1 | B12: Decisions sheet: new row — next ID (D-004, D-005…), date, title, confidence 1–5, tags, your thesis, and what you expect to happen.
A13: 2 | B13: Trades sheet: one row per executed trade with the SAME Decision ID and the same date.
A14: 3 | B14: Read the decision row: Ghost value (portfolio if you had done nothing), Acted value (portfolio after the trades) and Decision value ($ and %) fill automatically at CURRENT prices.
A15: P3 — RECORD DEPOSITS & WITHDRAWALS
A16: 1 | B16: CashEvents sheet: date, type (Deposit/Withdrawal), amount, note. Never put trades here. Deposits are excluded from returns — adding money never counts as gains.
A17: P4 — UPDATE PRICES (weekly routine; this grows your statistics)
A18: 1 | B18: Prices sheet: update Current price for every ticker including the benchmark.
A19: 2 | B19: Snapshots sheet: add ONE new row directly under the last filled row (no gaps): date + price per ticker column + benchmark price. Shares, cash, value, returns compute automatically (prefilled to row 40).
A20: 3 | B20: Risk statistics appear from 6 snapshots and firm up as history grows. The app is identical: each "Refresh prices" adds one snapshot.
A21: 4 | B21: Past row 40: fill the last row's formulas (columns M–AE) downward, and extend the Dashboard chart range.
A22: P5 — READ THE DASHBOARD
A23: 1 | B23: Account block: Portfolio value, Free funds, Invested, Unrealized/Realized P/L, Net deposits, Total return (vs net deposits), and "All decisions vs doing nothing".
A24: 2 | B24: Holdings table: shares, average cost, price, value, weight, sector per ticker. Equity chart plots the Snapshots value column.
A25: P6 — X-RAY REVIEW (monthly)
A26: 1 | B26: Sharpe: risk-adjusted return; >1 is good, >2 excellent — but only meaningful with months of snapshots.
A27: 2 | B27: Beta: ≈1 moves with the benchmark, <1 defensive, >1 amplified. Alpha: return above what your Beta alone would earn (CAPM). R²: how much the benchmark explains your moves.
A28: 3 | B28: Max drawdown: worst peak-to-trough of the time-weighted index. Concentration: effective holdings and largest-position weight. Sectors: complete once every ticker has a sector on Prices.
A29: P7 — REVIEW A DECISION
A30: 1 | B30: When a decision comes due, fill Review grade (A–F) and notes on its Decisions row. Grade the reasoning, not just the outcome.
A31: P8 — RECONCILE WITH THE APP
A32: 1 | B32: In the app (https://anhng211.github.io/trading-journal/): Settings → Load demo data. This workbook ships with the same dataset.
A33: 2 | B33: Open the Reconciliation sheet: every row compares an app figure to this workbook's formula. All Status cells must read PASS.
A34: 3 | B34: Running both with real data: after each app action, mirror it here (decision → Decisions + Trades; deposit → CashEvents; price refresh → Prices + one Snapshots row), then spot-check Portfolio value, Free funds and Total return.
A35: P9 — ADD A NEW TICKER (3 places)
A36: 1 | B36: Prices: add a row (ticker, price, sector, type).
A37: 2 | B37: Snapshots: type the ticker into an empty YELLOW slot header (F3–K3).
A38: 3 | B38: Dashboard: type the ticker into an empty Holdings row (A20–A24).
A39: P10 — LIMITATIONS VS THE APP
A40: 1 | B40: Visuals: only the equity chart is included (no slopegraph / ghost-chart graphics).
A41: 2 | B41: Cost basis: buying again AFTER a partial sell approximates average cost at later sales (the app computes the sequential weighted average). All-buys-then-sells is exact.
A42: 3 | B42: Snapshots must be contiguous and dated ascending; one decision per date. Full list on the Reconciliation sheet.

Sheet Settings
A1: Settings
A2: Blue cells are inputs; everything else in the workbook calculates from them.
A4: Starting cash ($) | B4: 25000 | C4: Cash at inception, before any trades or cash events. App: Settings → Initial deposit.
A5: Benchmark ticker | B5: SPY | C5: Beta/Alpha/R² compare against this. Fill its price in EVERY Snapshots row (column L).
A6: Risk-free rate (annual) | B6: 0.04 | C6: Used by the Sharpe ratio. App: X-Ray → "Risk-free %/yr".
A7: Demo anchor date | B7: 46204 | C7: Demo dates are fixed relative to this day. The app regenerates demo dates relative to "today"; day-offsets are identical, so statistics match.
A9: Source: app demo dataset (src/lib/demo.ts), values verified in the app UI on 2026-07-01.

Sheet Decisions
A1: Decisions — the journaling unit
A2: One row per decision; its trades live on the Trades sheet under the same Decision ID. Ghost/Acted/Decision value are calculated at CURRENT prices: "what you did" vs "if you had done nothing".
A3: Decision ID | B3: Date | C3: Title | D3: Confidence (1-5) | E3: Tags | F3: Thesis | G3: Expected | H3: Review grade | I3: Review notes | J3: Ghost value ($) | K3: Acted value ($) | L3: Decision value ($) | M3: Decision value (%)
A4: D-001 | B4: 46114 | C4: Build the core portfolio | D4: 4 | E4: core, long-term | F4: Broad-market core (VOO) plus AAPL quality compounding and INTC as a cheap turnaround bet. | G4: Beat cash over 12 months; INTC is the speculative sleeve. | J4: =IF($A4="","",Settings!$B$4+SUMIFS(CashEvents!$E$4:$E$30,CashEvents!$A$4:$A$30,"<"&$B4)+SUMIFS(Trades!$J$4:$J$40,Trades!$B$4:$B$40,"<"&$B4)+SUMPRODUCT(SUMIFS(Trades!$I$4:$I$40,Trades!$D$4:$D$40,Prices!$A$4:$A$13,Trades!$B$4:$B$40,"<"&$B4),Prices!$B$4:$B$13)) -> 25000 | K4: =IF($A4="","",Settings!$B$4+SUMIFS(CashEvents!$E$4:$E$30,CashEvents!$A$4:$A$30,"<="&$B4)+SUMIFS(Trades!$J$4:$J$40,Trades!$B$4:$B$40,"<="&$B4)+SUMPRODUCT(SUMIFS(Trades!$I$4:$I$40,Trades!$D$4:$D$40,Prices!$A$4:$A$13,Trades!$B$4:$B$40,"<="&$B4),Prices!$B$4:$B$13)) -> 25385 | L4: =IF($A4="","",$K4-$J4) -> 385 | M4: =IF($A4="","",IFERROR($L4/$J4,"")) -> 0.0154
A5: D-002 | B5: 46159 | C5: Rotate INTC into NVDA | D5: 4 | E5: rotation, semis | F5: INTC turnaround broke — foundry losses widening. Rotate into NVDA: datacenter demand under-modeled. | G5: NVDA outperforms INTC by 15%+ over 6 months. | H5: A | I5: Right call, right reason. Cut broken theses fast. | J5: =IF($A5="","",Settings!$B$4+SUMIFS(CashEvents!$E$4:$E$30,CashEvents!$A$4:$A$30,"<"&$B5)+SUMIFS(Trades!$J$4:$J$40,Trades!$B$4:$B$40,"<"&$B5)+SUMPRODUCT(SUMIFS(Trades!$I$4:$I$40,Trades!$D$4:$D$40,Prices!$A$4:$A$13,Trades!$B$4:$B$40,"<"&$B5),Prices!$B$4:$B$13)) -> 25385 | K5: =IF($A5="","",Settings!$B$4+SUMIFS(CashEvents!$E$4:$E$30,CashEvents!$A$4:$A$30,"<="&$B5)+SUMIFS(Trades!$J$4:$J$40,Trades!$B$4:$B$40,"<="&$B5)+SUMPRODUCT(SUMIFS(Trades!$I$4:$I$40,Trades!$D$4:$D$40,Prices!$A$4:$A$13,Trades!$B$4:$B$40,"<="&$B5),Prices!$B$4:$B$13)) -> 25835 | L5: =IF($A5="","",$K5-$J5) -> 450 | M5: =IF($A5="","",IFERROR($L5/$J5,"")) -> 0.017727004
A6: D-003 | B6: 46190 | C6: Trim AAPL, start MSFT | D6: 2 | E6: trim, rebalance | F6: AAPL grew past target weight; recycle a third into MSFT for Azure/AI exposure. | G6: MSFT roughly matches AAPL; diversification, not alpha. | J6: =IF($A6="","",Settings!$B$4+SUMIFS(CashEvents!$E$4:$E$30,CashEvents!$A$4:$A$30,"<"&$B6)+SUMIFS(Trades!$J$4:$J$40,Trades!$B$4:$B$40,"<"&$B6)+SUMPRODUCT(SUMIFS(Trades!$I$4:$I$40,Trades!$D$4:$D$40,Prices!$A$4:$A$13,Trades!$B$4:$B$40,"<"&$B6),Prices!$B$4:$B$13)) -> 28835 | K6: =IF($A6="","",Settings!$B$4+SUMIFS(CashEvents!$E$4:$E$30,CashEvents!$A$4:$A$30,"<="&$B6)+SUMIFS(Trades!$J$4:$J$40,Trades!$B$4:$B$40,"<="&$B6)+SUMPRODUCT(SUMIFS(Trades!$I$4:$I$40,Trades!$D$4:$D$40,Prices!$A$4:$A$13,Trades!$B$4:$B$40,"<="&$B6),Prices!$B$4:$B$13)) -> 28846 | L6: =IF($A6="","",$K6-$J6) -> 11 | M6: =IF($A6="","",IFERROR($L6/$J6,"")) -> 0.00038148084
J7: =IF($A7="","",Settings!$B$4+SUMIFS(CashEvents!$E$4:$E$30,CashEvents!$A$4:$A$30,"<"&$B7)+SUMIFS(Trades!$J$4:$J$40,Trades!$B$4:$B$40,"<"&$B7)+SUMPRODUCT(SUMIFS(Trades!$I$4:$I$40,Trades!$D$4:$D$40,Prices!$A$4:$A$13,Trades!$B$4:$B$40,"<"&$B7),Prices!$B$4:$B$13)) | K7: =IF($A7="","",Settings!$B$4+SUMIFS(CashEvents!$E$4:$E$30,CashEvents!$A$4:$A$30,"<="&$B7)+SUMIFS(Trades!$J$4:$J$40,Trades!$B$4:$B$40,"<="&$B7)+SUMPRODUCT(SUMIFS(Trades!$I$4:$I$40,Trades!$D$4:$D$40,Prices!$A$4:$A$13,Trades!$B$4:$B$40,"<="&$B7),Prices!$B$4:$B$13)) | L7: =IF($A7="","",$K7-$J7) | M7: =IF($A7="","",IFERROR($L7/$J7,""))
J8: =IF($A8="","",Settings!$B$4+SUMIFS(CashEvents!$E$4:$E$30,CashEvents!$A$4:$A$30,"<"&$B8)+SUMIFS(Trades!$J$4:$J$40,Trades!$B$4:$B$40,"<"&$B8)+SUMPRODUCT(SUMIFS(Trades!$I$4:$I$40,Trades!$D$4:$D$40,Prices!$A$4:$A$13,Trades!$B$4:$B$40,"<"&$B8),Prices!$B$4:$B$13)) | K8: =IF($A8="","",Settings!$B$4+SUMIFS(CashEvents!$E$4:$E$30,CashEvents!$A$4:$A$30,"<="&$B8)+SUMIFS(Trades!$J$4:$J$40,Trades!$B$4:$B$40,"<="&$B8)+SUMPRODUCT(SUMIFS(Trades!$I$4:$I$40,Trades!$D$4:$D$40,Prices!$A$4:$A$13,Trades!$B$4:$B$40,"<="&$B8),Prices!$B$4:$B$13)) | L8: =IF($A8="","",$K8-$J8) | M8: =IF($A8="","",IFERROR($L8/$J8,""))
J9: =IF($A9="","",Settings!$B$4+SUMIFS(CashEvents!$E$4:$E$30,CashEvents!$A$4:$A$30,"<"&$B9)+SUMIFS(Trades!$J$4:$J$40,Trades!$B$4:$B$40,"<"&$B9)+SUMPRODUCT(SUMIFS(Trades!$I$4:$I$40,Trades!$D$4:$D$40,Prices!$A$4:$A$13,Trades!$B$4:$B$40,"<"&$B9),Prices!$B$4:$B$13)) | K9: =IF($A9="","",Settings!$B$4+SUMIFS(CashEvents!$E$4:$E$30,CashEvents!$A$4:$A$30,"<="&$B9)+SUMIFS(Trades!$J$4:$J$40,Trades!$B$4:$B$40,"<="&$B9)+SUMPRODUCT(SUMIFS(Trades!$I$4:$I$40,Trades!$D$4:$D$40,Prices!$A$4:$A$13,Trades!$B$4:$B$40,"<="&$B9),Prices!$B$4:$B$13)) | L9: =IF($A9="","",$K9-$J9) | M9: =IF($A9="","",IFERROR($L9/$J9,""))
J10: =IF($A10="","",Settings!$B$4+SUMIFS(CashEvents!$E$4:$E$30,CashEvents!$A$4:$A$30,"<"&$B10)+SUMIFS(Trades!$J$4:$J$40,Trades!$B$4:$B$40,"<"&$B10)+SUMPRODUCT(SUMIFS(Trades!$I$4:$I$40,Trades!$D$4:$D$40,Prices!$A$4:$A$13,Trades!$B$4:$B$40,"<"&$B10),Prices!$B$4:$B$13)) | K10: =IF($A10="","",Settings!$B$4+SUMIFS(CashEvents!$E$4:$E$30,CashEvents!$A$4:$A$30,"<="&$B10)+SUMIFS(Trades!$J$4:$J$40,Trades!$B$4:$B$40,"<="&$B10)+SUMPRODUCT(SUMIFS(Trades!$I$4:$I$40,Trades!$D$4:$D$40,Prices!$A$4:$A$13,Trades!$B$4:$B$40,"<="&$B10),Prices!$B$4:$B$13)) | L10: =IF($A10="","",$K10-$J10) | M10: =IF($A10="","",IFERROR($L10/$J10,""))
J11: =IF($A11="","",Settings!$B$4+SUMIFS(CashEvents!$E$4:$E$30,CashEvents!$A$4:$A$30,"<"&$B11)+SUMIFS(Trades!$J$4:$J$40,Trades!$B$4:$B$40,"<"&$B11)+SUMPRODUCT(SUMIFS(Trades!$I$4:$I$40,Trades!$D$4:$D$40,Prices!$A$4:$A$13,Trades!$B$4:$B$40,"<"&$B11),Prices!$B$4:$B$13)) | K11: =IF($A11="","",Settings!$B$4+SUMIFS(CashEvents!$E$4:$E$30,CashEvents!$A$4:$A$30,"<="&$B11)+SUMIFS(Trades!$J$4:$J$40,Trades!$B$4:$B$40,"<="&$B11)+SUMPRODUCT(SUMIFS(Trades!$I$4:$I$40,Trades!$D$4:$D$40,Prices!$A$4:$A$13,Trades!$B$4:$B$40,"<="&$B11),Prices!$B$4:$B$13)) | L11: =IF($A11="","",$K11-$J11) | M11: =IF($A11="","",IFERROR($L11/$J11,""))
J12: =IF($A12="","",Settings!$B$4+SUMIFS(CashEvents!$E$4:$E$30,CashEvents!$A$4:$A$30,"<"&$B12)+SUMIFS(Trades!$J$4:$J$40,Trades!$B$4:$B$40,"<"&$B12)+SUMPRODUCT(SUMIFS(Trades!$I$4:$I$40,Trades!$D$4:$D$40,Prices!$A$4:$A$13,Trades!$B$4:$B$40,"<"&$B12),Prices!$B$4:$B$13)) | K12: =IF($A12="","",Settings!$B$4+SUMIFS(CashEvents!$E$4:$E$30,CashEvents!$A$4:$A$30,"<="&$B12)+SUMIFS(Trades!$J$4:$J$40,Trades!$B$4:$B$40,"<="&$B12)+SUMPRODUCT(SUMIFS(Trades!$I$4:$I$40,Trades!$D$4:$D$40,Prices!$A$4:$A$13,Trades!$B$4:$B$40,"<="&$B12),Prices!$B$4:$B$13)) | L12: =IF($A12="","",$K12-$J12) | M12: =IF($A12="","",IFERROR($L12/$J12,""))
J13: =IF($A13="","",Settings!$B$4+SUMIFS(CashEvents!$E$4:$E$30,CashEvents!$A$4:$A$30,"<"&$B13)+SUMIFS(Trades!$J$4:$J$40,Trades!$B$4:$B$40,"<"&$B13)+SUMPRODUCT(SUMIFS(Trades!$I$4:$I$40,Trades!$D$4:$D$40,Prices!$A$4:$A$13,Trades!$B$4:$B$40,"<"&$B13),Prices!$B$4:$B$13)) | K13: =IF($A13="","",Settings!$B$4+SUMIFS(CashEvents!$E$4:$E$30,CashEvents!$A$4:$A$30,"<="&$B13)+SUMIFS(Trades!$J$4:$J$40,Trades!$B$4:$B$40,"<="&$B13)+SUMPRODUCT(SUMIFS(Trades!$I$4:$I$40,Trades!$D$4:$D$40,Prices!$A$4:$A$13,Trades!$B$4:$B$40,"<="&$B13),Prices!$B$4:$B$13)) | L13: =IF($A13="","",$K13-$J13) | M13: =IF($A13="","",IFERROR($L13/$J13,""))
J14: =IF($A14="","",Settings!$B$4+SUMIFS(CashEvents!$E$4:$E$30,CashEvents!$A$4:$A$30,"<"&$B14)+SUMIFS(Trades!$J$4:$J$40,Trades!$B$4:$B$40,"<"&$B14)+SUMPRODUCT(SUMIFS(Trades!$I$4:$I$40,Trades!$D$4:$D$40,Prices!$A$4:$A$13,Trades!$B$4:$B$40,"<"&$B14),Prices!$B$4:$B$13)) | K14: =IF($A14="","",Settings!$B$4+SUMIFS(CashEvents!$E$4:$E$30,CashEvents!$A$4:$A$30,"<="&$B14)+SUMIFS(Trades!$J$4:$J$40,Trades!$B$4:$B$40,"<="&$B14)+SUMPRODUCT(SUMIFS(Trades!$I$4:$I$40,Trades!$D$4:$D$40,Prices!$A$4:$A$13,Trades!$B$4:$B$40,"<="&$B14),Prices!$B$4:$B$13)) | L14: =IF($A14="","",$K14-$J14) | M14: =IF($A14="","",IFERROR($L14/$J14,""))
J15: =IF($A15="","",Settings!$B$4+SUMIFS(CashEvents!$E$4:$E$30,CashEvents!$A$4:$A$30,"<"&$B15)+SUMIFS(Trades!$J$4:$J$40,Trades!$B$4:$B$40,"<"&$B15)+SUMPRODUCT(SUMIFS(Trades!$I$4:$I$40,Trades!$D$4:$D$40,Prices!$A$4:$A$13,Trades!$B$4:$B$40,"<"&$B15),Prices!$B$4:$B$13)) | K15: =IF($A15="","",Settings!$B$4+SUMIFS(CashEvents!$E$4:$E$30,CashEvents!$A$4:$A$30,"<="&$B15)+SUMIFS(Trades!$J$4:$J$40,Trades!$B$4:$B$40,"<="&$B15)+SUMPRODUCT(SUMIFS(Trades!$I$4:$I$40,Trades!$D$4:$D$40,Prices!$A$4:$A$13,Trades!$B$4:$B$40,"<="&$B15),Prices!$B$4:$B$13)) | L15: =IF($A15="","",$K15-$J15) | M15: =IF($A15="","",IFERROR($L15/$J15,""))
J16: =IF($A16="","",Settings!$B$4+SUMIFS(CashEvents!$E$4:$E$30,CashEvents!$A$4:$A$30,"<"&$B16)+SUMIFS(Trades!$J$4:$J$40,Trades!$B$4:$B$40,"<"&$B16)+SUMPRODUCT(SUMIFS(Trades!$I$4:$I$40,Trades!$D$4:$D$40,Prices!$A$4:$A$13,Trades!$B$4:$B$40,"<"&$B16),Prices!$B$4:$B$13)) | K16: =IF($A16="","",Settings!$B$4+SUMIFS(CashEvents!$E$4:$E$30,CashEvents!$A$4:$A$30,"<="&$B16)+SUMIFS(Trades!$J$4:$J$40,Trades!$B$4:$B$40,"<="&$B16)+SUMPRODUCT(SUMIFS(Trades!$I$4:$I$40,Trades!$D$4:$D$40,Prices!$A$4:$A$13,Trades!$B$4:$B$40,"<="&$B16),Prices!$B$4:$B$13)) | L16: =IF($A16="","",$K16-$J16) | M16: =IF($A16="","",IFERROR($L16/$J16,""))
J17: =IF($A17="","",Settings!$B$4+SUMIFS(CashEvents!$E$4:$E$30,CashEvents!$A$4:$A$30,"<"&$B17)+SUMIFS(Trades!$J$4:$J$40,Trades!$B$4:$B$40,"<"&$B17)+SUMPRODUCT(SUMIFS(Trades!$I$4:$I$40,Trades!$D$4:$D$40,Prices!$A$4:$A$13,Trades!$B$4:$B$40,"<"&$B17),Prices!$B$4:$B$13)) | K17: =IF($A17="","",Settings!$B$4+SUMIFS(CashEvents!$E$4:$E$30,CashEvents!$A$4:$A$30,"<="&$B17)+SUMIFS(Trades!$J$4:$J$40,Trades!$B$4:$B$40,"<="&$B17)+SUMPRODUCT(SUMIFS(Trades!$I$4:$I$40,Trades!$D$4:$D$40,Prices!$A$4:$A$13,Trades!$B$4:$B$40,"<="&$B17),Prices!$B$4:$B$13)) | L17: =IF($A17="","",$K17-$J17) | M17: =IF($A17="","",IFERROR($L17/$J17,""))
J18: =IF($A18="","",Settings!$B$4+SUMIFS(CashEvents!$E$4:$E$30,CashEvents!$A$4:$A$30,"<"&$B18)+SUMIFS(Trades!$J$4:$J$40,Trades!$B$4:$B$40,"<"&$B18)+SUMPRODUCT(SUMIFS(Trades!$I$4:$I$40,Trades!$D$4:$D$40,Prices!$A$4:$A$13,Trades!$B$4:$B$40,"<"&$B18),Prices!$B$4:$B$13)) | K18: =IF($A18="","",Settings!$B$4+SUMIFS(CashEvents!$E$4:$E$30,CashEvents!$A$4:$A$30,"<="&$B18)+SUMIFS(Trades!$J$4:$J$40,Trades!$B$4:$B$40,"<="&$B18)+SUMPRODUCT(SUMIFS(Trades!$I$4:$I$40,Trades!$D$4:$D$40,Prices!$A$4:$A$13,Trades!$B$4:$B$40,"<="&$B18),Prices!$B$4:$B$13)) | L18: =IF($A18="","",$K18-$J18) | M18: =IF($A18="","",IFERROR($L18/$J18,""))
... J20: =IF($A20="","",Settings!$B$4+SUMIFS(CashEvents!$E$4:$E$30,CashEvents!$A$4:$A$30,"<"&$B20)+SUMIFS(Trades!$J$4:$J$40,Trades!$B$4:$B$40,"<"&$B20)+SUMPRODUCT(SUMIFS(Trades!$I$4:$I$40,Trades!$D$4:$D$40,Prices!$A$4:$A$13,Trades!$B$4:$B$40,"<"&$B20),Prices!$B$4:$B$13)) | K20: =IF($A20="","",Settings!$B$4+SUMIFS(CashEvents!$E$4:$E$30,CashEvents!$A$4:$A$30,"<="&$B20)+SUMIFS(Trades!$J$4:$J$40,Trades!$B$4:$B$40,"<="&$B20)+SUMPRODUCT(SUMIFS(Trades!$I$4:$I$40,Trades!$D$4:$D$40,Prices!$A$4:$A$13,Trades!$B$4:$B$40,"<="&$B20),Prices!$B$4:$B$13)) | L20: =IF($A20="","",$K20-$J20) | M20: =IF($A20="","",IFERROR($L20/$J20,""))

Sheet Trades
A1: Trades — every buy and sell
A2: Each row belongs to a decision (Decision ID). Columns I–L are calculated.
A3: Trade ID | B3: Date | C3: Decision ID | D3: Ticker | E3: Side (Buy/Sell) | F3: Shares | G3: Price ($) | H3: Fees ($) | I3: Signed shares | J3: Cash flow ($) | K3: Avg cost @ sale ($) | L3: Realized P/L ($)
A4: T-01 | B4: 46114 | C4: D-001 | D4: VOO | E4: Buy | F4: 20 | G4: 480 | H4: 0 | I4: =IF($D4="","",IF($E4="Buy",$F4,-$F4)) -> 20 | J4: =IF($D4="","",IF($E4="Buy",-($F4*$G4+$H4),$F4*$G4-$H4)) -> -9600 | K4: =IF(OR($D4="",$E4<>"Sell"),"",IFERROR(SUMPRODUCT(($D$4:$D$40=$D4)*($E$4:$E$40="Buy")*($B$4:$B$40<=$B4)*($F$4:$F$40*$G$4:$G$40+$H$4:$H$40))/SUMPRODUCT(($D$4:$D$40=$D4)*($E$4:$E$40="Buy")*($B$4:$B$40<=$B4)*$F$4:$F$40),"")) | L4: =IF(OR($D4="",$E4<>"Sell"),"",($G4-$K4)*$F4-$H4)
A5: T-02 | B5: 46114 | C5: D-001 | D5: AAPL | E5: Buy | F5: 15 | G5: 220 | H5: 0 | I5: =IF($D5="","",IF($E5="Buy",$F5,-$F5)) -> 15 | J5: =IF($D5="","",IF($E5="Buy",-($F5*$G5+$H5),$F5*$G5-$H5)) -> -3300 | K5: =IF(OR($D5="",$E5<>"Sell"),"",IFERROR(SUMPRODUCT(($D$4:$D$40=$D5)*($E$4:$E$40="Buy")*($B$4:$B$40<=$B5)*($F$4:$F$40*$G$4:$G$40+$H$4:$H$40))/SUMPRODUCT(($D$4:$D$40=$D5)*($E$4:$E$40="Buy")*($B$4:$B$40<=$B5)*$F$4:$F$40),"")) | L5: =IF(OR($D5="",$E5<>"Sell"),"",($G5-$K5)*$F5-$H5)
A6: T-03 | B6: 46114 | C6: D-001 | D6: INTC | E6: Buy | F6: 40 | G6: 35 | H6: 0 | I6: =IF($D6="","",IF($E6="Buy",$F6,-$F6)) -> 40 | J6: =IF($D6="","",IF($E6="Buy",-($F6*$G6+$H6),$F6*$G6-$H6)) -> -1400 | K6: =IF(OR($D6="",$E6<>"Sell"),"",IFERROR(SUMPRODUCT(($D$4:$D$40=$D6)*($E$4:$E$40="Buy")*($B$4:$B$40<=$B6)*($F$4:$F$40*$G$4:$G$40+$H$4:$H$40))/SUMPRODUCT(($D$4:$D$40=$D6)*($E$4:$E$40="Buy")*($B$4:$B$40<=$B6)*$F$4:$F$40),"")) | L6: =IF(OR($D6="",$E6<>"Sell"),"",($G6-$K6)*$F6-$H6)
A7: T-04 | B7: 46159 | C7: D-002 | D7: INTC | E7: Sell | F7: 40 | G7: 30 | H7: 0 | I7: =IF($D7="","",IF($E7="Buy",$F7,-$F7)) -> -40 | J7: =IF($D7="","",IF($E7="Buy",-($F7*$G7+$H7),$F7*$G7-$H7)) -> 1200 | K7: =IF(OR($D7="",$E7<>"Sell"),"",IFERROR(SUMPRODUCT(($D$4:$D$40=$D7)*($E$4:$E$40="Buy")*($B$4:$B$40<=$B7)*($F$4:$F$40*$G$4:$G$40+$H$4:$H$40))/SUMPRODUCT(($D$4:$D$40=$D7)*($E$4:$E$40="Buy")*($B$4:$B$40<=$B7)*$F$4:$F$40),"")) -> 35 | L7: =IF(OR($D7="",$E7<>"Sell"),"",($G7-$K7)*$F7-$H7) -> -200
A8: T-05 | B8: 46159 | C8: D-002 | D8: NVDA | E8: Buy | F8: 10 | G8: 120 | H8: 0 | I8: =IF($D8="","",IF($E8="Buy",$F8,-$F8)) -> 10 | J8: =IF($D8="","",IF($E8="Buy",-($F8*$G8+$H8),$F8*$G8-$H8)) -> -1200 | K8: =IF(OR($D8="",$E8<>"Sell"),"",IFERROR(SUMPRODUCT(($D$4:$D$40=$D8)*($E$4:$E$40="Buy")*($B$4:$B$40<=$B8)*($F$4:$F$40*$G$4:$G$40+$H$4:$H$40))/SUMPRODUCT(($D$4:$D$40=$D8)*($E$4:$E$40="Buy")*($B$4:$B$40<=$B8)*$F$4:$F$40),"")) | L8: =IF(OR($D8="",$E8<>"Sell"),"",($G8-$K8)*$F8-$H8)
A9: T-06 | B9: 46190 | C9: D-003 | D9: AAPL | E9: Sell | F9: 5 | G9: 230 | H9: 0 | I9: =IF($D9="","",IF($E9="Buy",$F9,-$F9)) -> -5 | J9: =IF($D9="","",IF($E9="Buy",-($F9*$G9+$H9),$F9*$G9-$H9)) -> 1150 | K9: =IF(OR($D9="",$E9<>"Sell"),"",IFERROR(SUMPRODUCT(($D$4:$D$40=$D9)*($E$4:$E$40="Buy")*($B$4:$B$40<=$B9)*($F$4:$F$40*$G$4:$G$40+$H$4:$H$40))/SUMPRODUCT(($D$4:$D$40=$D9)*($E$4:$E$40="Buy")*($B$4:$B$40<=$B9)*$F$4:$F$40),"")) -> 220 | L9: =IF(OR($D9="",$E9<>"Sell"),"",($G9-$K9)*$F9-$H9) -> 50
A10: T-07 | B10: 46190 | C10: D-003 | D10: MSFT | E10: Buy | F10: 3 | G10: 420 | H10: 0 | I10: =IF($D10="","",IF($E10="Buy",$F10,-$F10)) -> 3 | J10: =IF($D10="","",IF($E10="Buy",-($F10*$G10+$H10),$F10*$G10-$H10)) -> -1260 | K10: =IF(OR($D10="",$E10<>"Sell"),"",IFERROR(SUMPRODUCT(($D$4:$D$40=$D10)*($E$4:$E$40="Buy")*($B$4:$B$40<=$B10)*($F$4:$F$40*$G$4:$G$40+$H$4:$H$40))/SUMPRODUCT(($D$4:$D$40=$D10)*($E$4:$E$40="Buy")*($B$4:$B$40<=$B10)*$F$4:$F$40),"")) | L10: =IF(OR($D10="",$E10<>"Sell"),"",($G10-$K10)*$F10-$H10)
I11: =IF($D11="","",IF($E11="Buy",$F11,-$F11)) | J11: =IF($D11="","",IF($E11="Buy",-($F11*$G11+$H11),$F11*$G11-$H11)) | K11: =IF(OR($D11="",$E11<>"Sell"),"",IFERROR(SUMPRODUCT(($D$4:$D$40=$D11)*($E$4:$E$40="Buy")*($B$4:$B$40<=$B11)*($F$4:$F$40*$G$4:$G$40+$H$4:$H$40))/SUMPRODUCT(($D$4:$D$40=$D11)*($E$4:$E$40="Buy")*($B$4:$B$40<=$B11)*$F$4:$F$40),"")) | L11: =IF(OR($D11="",$E11<>"Sell"),"",($G11-$K11)*$F11-$H11)
I12: =IF($D12="","",IF($E12="Buy",$F12,-$F12)) | J12: =IF($D12="","",IF($E12="Buy",-($F12*$G12+$H12),$F12*$G12-$H12)) | K12: =IF(OR($D12="",$E12<>"Sell"),"",IFERROR(SUMPRODUCT(($D$4:$D$40=$D12)*($E$4:$E$40="Buy")*($B$4:$B$40<=$B12)*($F$4:$F$40*$G$4:$G$40+$H$4:$H$40))/SUMPRODUCT(($D$4:$D$40=$D12)*($E$4:$E$40="Buy")*($B$4:$B$40<=$B12)*$F$4:$F$40),"")) | L12: =IF(OR($D12="",$E12<>"Sell"),"",($G12-$K12)*$F12-$H12)
I13: =IF($D13="","",IF($E13="Buy",$F13,-$F13)) | J13: =IF($D13="","",IF($E13="Buy",-($F13*$G13+$H13),$F13*$G13-$H13)) | K13: =IF(OR($D13="",$E13<>"Sell"),"",IFERROR(SUMPRODUCT(($D$4:$D$40=$D13)*($E$4:$E$40="Buy")*($B$4:$B$40<=$B13)*($F$4:$F$40*$G$4:$G$40+$H$4:$H$40))/SUMPRODUCT(($D$4:$D$40=$D13)*($E$4:$E$40="Buy")*($B$4:$B$40<=$B13)*$F$4:$F$40),"")) | L13: =IF(OR($D13="",$E13<>"Sell"),"",($G13-$K13)*$F13-$H13)
I14: =IF($D14="","",IF($E14="Buy",$F14,-$F14)) | J14: =IF($D14="","",IF($E14="Buy",-($F14*$G14+$H14),$F14*$G14-$H14)) | K14: =IF(OR($D14="",$E14<>"Sell"),"",IFERROR(SUMPRODUCT(($D$4:$D$40=$D14)*($E$4:$E$40="Buy")*($B$4:$B$40<=$B14)*($F$4:$F$40*$G$4:$G$40+$H$4:$H$40))/SUMPRODUCT(($D$4:$D$40=$D14)*($E$4:$E$40="Buy")*($B$4:$B$40<=$B14)*$F$4:$F$40),"")) | L14: =IF(OR($D14="",$E14<>"Sell"),"",($G14-$K14)*$F14-$H14)
I15: =IF($D15="","",IF($E15="Buy",$F15,-$F15)) | J15: =IF($D15="","",IF($E15="Buy",-($F15*$G15+$H15),$F15*$G15-$H15)) | K15: =IF(OR($D15="",$E15<>"Sell"),"",IFERROR(SUMPRODUCT(($D$4:$D$40=$D15)*($E$4:$E$40="Buy")*($B$4:$B$40<=$B15)*($F$4:$F$40*$G$4:$G$40+$H$4:$H$40))/SUMPRODUCT(($D$4:$D$40=$D15)*($E$4:$E$40="Buy")*($B$4:$B$40<=$B15)*$F$4:$F$40),"")) | L15: =IF(OR($D15="",$E15<>"Sell"),"",($G15-$K15)*$F15-$H15)
I16: =IF($D16="","",IF($E16="Buy",$F16,-$F16)) | J16: =IF($D16="","",IF($E16="Buy",-($F16*$G16+$H16),$F16*$G16-$H16)) | K16: =IF(OR($D16="",$E16<>"Sell"),"",IFERROR(SUMPRODUCT(($D$4:$D$40=$D16)*($E$4:$E$40="Buy")*($B$4:$B$40<=$B16)*($F$4:$F$40*$G$4:$G$40+$H$4:$H$40))/SUMPRODUCT(($D$4:$D$40=$D16)*($E$4:$E$40="Buy")*($B$4:$B$40<=$B16)*$F$4:$F$40),"")) | L16: =IF(OR($D16="",$E16<>"Sell"),"",($G16-$K16)*$F16-$H16)
I17: =IF($D17="","",IF($E17="Buy",$F17,-$F17)) | J17: =IF($D17="","",IF($E17="Buy",-($F17*$G17+$H17),$F17*$G17-$H17)) | K17: =IF(OR($D17="",$E17<>"Sell"),"",IFERROR(SUMPRODUCT(($D$4:$D$40=$D17)*($E$4:$E$40="Buy")*($B$4:$B$40<=$B17)*($F$4:$F$40*$G$4:$G$40+$H$4:$H$40))/SUMPRODUCT(($D$4:$D$40=$D17)*($E$4:$E$40="Buy")*($B$4:$B$40<=$B17)*$F$4:$F$40),"")) | L17: =IF(OR($D17="",$E17<>"Sell"),"",($G17-$K17)*$F17-$H17)
I18: =IF($D18="","",IF($E18="Buy",$F18,-$F18)) | J18: =IF($D18="","",IF($E18="Buy",-($F18*$G18+$H18),$F18*$G18-$H18)) | K18: =IF(OR($D18="",$E18<>"Sell"),"",IFERROR(SUMPRODUCT(($D$4:$D$40=$D18)*($E$4:$E$40="Buy")*($B$4:$B$40<=$B18)*($F$4:$F$40*$G$4:$G$40+$H$4:$H$40))/SUMPRODUCT(($D$4:$D$40=$D18)*($E$4:$E$40="Buy")*($B$4:$B$40<=$B18)*$F$4:$F$40),"")) | L18: =IF(OR($D18="",$E18<>"Sell"),"",($G18-$K18)*$F18-$H18)
I19: =IF($D19="","",IF($E19="Buy",$F19,-$F19)) | J19: =IF($D19="","",IF($E19="Buy",-($F19*$G19+$H19),$F19*$G19-$H19)) | K19: =IF(OR($D19="",$E19<>"Sell"),"",IFERROR(SUMPRODUCT(($D$4:$D$40=$D19)*($E$4:$E$40="Buy")*($B$4:$B$40<=$B19)*($F$4:$F$40*$G$4:$G$40+$H$4:$H$40))/SUMPRODUCT(($D$4:$D$40=$D19)*($E$4:$E$40="Buy")*($B$4:$B$40<=$B19)*$F$4:$F$40),"")) | L19: =IF(OR($D19="",$E19<>"Sell"),"",($G19-$K19)*$F19-$H19)
I20: =IF($D20="","",IF($E20="Buy",$F20,-$F20)) | J20: =IF($D20="","",IF($E20="Buy",-($F20*$G20+$H20),$F20*$G20-$H20)) | K20: =IF(OR($D20="",$E20<>"Sell"),"",IFERROR(SUMPRODUCT(($D$4:$D$40=$D20)*($E$4:$E$40="Buy")*($B$4:$B$40<=$B20)*($F$4:$F$40*$G$4:$G$40+$H$4:$H$40))/SUMPRODUCT(($D$4:$D$40=$D20)*($E$4:$E$40="Buy")*($B$4:$B$40<=$B20)*$F$4:$F$40),"")) | L20: =IF(OR($D20="",$E20<>"Sell"),"",($G20-$K20)*$F20-$H20)
I21: =IF($D21="","",IF($E21="Buy",$F21,-$F21)) | J21: =IF($D21="","",IF($E21="Buy",-($F21*$G21+$H21),$F21*$G21-$H21)) | K21: =IF(OR($D21="",$E21<>"Sell"),"",IFERROR(SUMPRODUCT(($D$4:$D$40=$D21)*($E$4:$E$40="Buy")*($B$4:$B$40<=$B21)*($F$4:$F$40*$G$4:$G$40+$H$4:$H$40))/SUMPRODUCT(($D$4:$D$40=$D21)*($E$4:$E$40="Buy")*($B$4:$B$40<=$B21)*$F$4:$F$40),"")) | L21: =IF(OR($D21="",$E21<>"Sell"),"",($G21-$K21)*$F21-$H21)
I22: =IF($D22="","",IF($E22="Buy",$F22,-$F22)) | J22: =IF($D22="","",IF($E22="Buy",-($F22*$G22+$H22),$F22*$G22-$H22)) | K22: =IF(OR($D22="",$E22<>"Sell"),"",IFERROR(SUMPRODUCT(($D$4:$D$40=$D22)*($E$4:$E$40="Buy")*($B$4:$B$40<=$B22)*($F$4:$F$40*$G$4:$G$40+$H$4:$H$40))/SUMPRODUCT(($D$4:$D$40=$D22)*($E$4:$E$40="Buy")*($B$4:$B$40<=$B22)*$F$4:$F$40),"")) | L22: =IF(OR($D22="",$E22<>"Sell"),"",($G22-$K22)*$F22-$H22)
... I40: =IF($D40="","",IF($E40="Buy",$F40,-$F40)) | J40: =IF($D40="","",IF($E40="Buy",-($F40*$G40+$H40),$F40*$G40-$H40)) | K40: =IF(OR($D40="",$E40<>"Sell"),"",IFERROR(SUMPRODUCT(($D$4:$D$40=$D40)*($E$4:$E$40="Buy")*($B$4:$B$40<=$B40)*($F$4:$F$40*$G$4:$G$40+$H$4:$H$40))/SUMPRODUCT(($D$4:$D$40=$D40)*($E$4:$E$40="Buy")*($B$4:$B$40<=$B40)*$F$4:$F$40),"")) | L40: =IF(OR($D40="",$E40<>"Sell"),"",($G40-$K40)*$F40-$H40)

Sheet CashEvents
A1: Cash Events — deposits & withdrawals
A2: External money in/out only (trades never go here). Signed amount is calculated.
A3: Date | B3: Type (Deposit/Withdrawal) | C3: Amount ($) | D3: Note | E3: Signed ($)
A4: 46164 | B4: Deposit | C4: 3000 | D4: Monthly savings top-up | E4: =IF($B4="","",IF($B4="Deposit",$C4,-$C4)) -> 3000
E5: =IF($B5="","",IF($B5="Deposit",$C5,-$C5))
E6: =IF($B6="","",IF($B6="Deposit",$C6,-$C6))
E7: =IF($B7="","",IF($B7="Deposit",$C7,-$C7))
E8: =IF($B8="","",IF($B8="Deposit",$C8,-$C8))
E9: =IF($B9="","",IF($B9="Deposit",$C9,-$C9))
E10: =IF($B10="","",IF($B10="Deposit",$C10,-$C10))
E11: =IF($B11="","",IF($B11="Deposit",$C11,-$C11))
E12: =IF($B12="","",IF($B12="Deposit",$C12,-$C12))
E13: =IF($B13="","",IF($B13="Deposit",$C13,-$C13))
E14: =IF($B14="","",IF($B14="Deposit",$C14,-$C14))
E15: =IF($B15="","",IF($B15="Deposit",$C15,-$C15))
E16: =IF($B16="","",IF($B16="Deposit",$C16,-$C16))
... E30: =IF($B30="","",IF($B30="Deposit",$C30,-$C30))

Sheet Prices
A1: Prices — current quote per ticker
A2: Update Price on every refresh. Sector & Type feed the X-Ray (the app auto-fills these from Finnhub; here you type them).
A3: Ticker | B3: Current price ($) | C3: Sector | D3: Type (stock/etf)
A4: VOO | B4: 510 | C4: ETF / Fund | D4: etf
A5: AAPL | B5: 235 | C5: Technology | D5: stock
A6: NVDA | B6: 141 | C6: Semiconductors | D6: stock
A7: MSFT | B7: 432 | C7: Software | D7: stock
A8: INTC | B8: 24 | C8: Semiconductors | D8: stock
A9: SPY | B9: 555 | C9: ETF / Fund | D9: etf
A15: Source: app demo price cache (last snapshot, 2026-06-30).

Sheet Snapshots
A1: Snapshots — price history (one row per refresh)
A2: Enter date + prices (blue). Yellow headers B3:K3 are editable ticker slots. Everything from M onward is calculated: shares held, cash, value, flow-adjusted returns, drawdown.
A3: Date | B3: VOO | C3: AAPL | D3: INTC | E3: NVDA | F3: MSFT | L3: Benchmark (SPY) | M3: =IF(B$3="","·",B$3&" sh") -> VOO sh | N3: =IF(C$3="","·",C$3&" sh") -> AAPL sh | O3: =IF(D$3="","·",D$3&" sh") -> INTC sh | P3: =IF(E$3="","·",E$3&" sh") -> NVDA sh | Q3: =IF(F$3="","·",F$3&" sh") -> MSFT sh | R3: =IF(G$3="","·",G$3&" sh") -> · | S3: =IF(H$3="","·",H$3&" sh") -> · | T3: =IF(I$3="","·",I$3&" sh") -> · | ... V3: =IF(K$3="","·",K$3&" sh") -> · | W3: Cash ($) | X3: Portfolio value ($) | Y3: Net flow ($) | Z3: Portfolio return | AA3: Benchmark return | AB3: TWR index | AC3: Peak | AD3: Drawdown | AE3: Bench index
A4: 46129 | B4: 485 | C4: 222 | D4: 33 | L4: 528 | M4: =IF($A4="",0,SUMIFS(Trades!$I$4:$I$40,Trades!$D$4:$D$40,B$3,Trades!$B$4:$B$40,"<="&$A4)) -> 20 | N4: =IF($A4="",0,SUMIFS(Trades!$I$4:$I$40,Trades!$D$4:$D$40,C$3,Trades!$B$4:$B$40,"<="&$A4)) -> 15 | O4: =IF($A4="",0,SUMIFS(Trades!$I$4:$I$40,Trades!$D$4:$D$40,D$3,Trades!$B$4:$B$40,"<="&$A4)) -> 40 | P4: =IF($A4="",0,SUMIFS(Trades!$I$4:$I$40,Trades!$D$4:$D$40,E$3,Trades!$B$4:$B$40,"<="&$A4)) -> 0 | Q4: =IF($A4="",0,SUMIFS(Trades!$I$4:$I$40,Trades!$D$4:$D$40,F$3,Trades!$B$4:$B$40,"<="&$A4)) -> 0 | R4: =IF($A4="",0,SUMIFS(Trades!$I$4:$I$40,Trades!$D$4:$D$40,G$3,Trades!$B$4:$B$40,"<="&$A4)) -> 0 | S4: =IF($A4="",0,SUMIFS(Trades!$I$4:$I$40,Trades!$D$4:$D$40,H$3,Trades!$B$4:$B$40,"<="&$A4)) -> 0 | T4: =IF($A4="",0,SUMIFS(Trades!$I$4:$I$40,Trades!$D$4:$D$40,I$3,Trades!$B$4:$B$40,"<="&$A4)) -> 0 | ... V4: =IF($A4="",0,SUMIFS(Trades!$I$4:$I$40,Trades!$D$4:$D$40,K$3,Trades!$B$4:$B$40,"<="&$A4)) -> 0 | W4: =IF($A4="",0,Settings!$B$4+SUMIFS(CashEvents!$E$4:$E$30,CashEvents!$A$4:$A$30,"<="&$A4)+SUMIFS(Trades!$J$4:$J$40,Trades!$B$4:$B$40,"<="&$A4)) -> 10700 | X4: =IF($A4="","",SUMPRODUCT($B4:$K4,$M4:$V4)+$W4) -> 25050 | AB4: =IF($A4="","",1) -> 1 | AE4: =IF($A4="","",1) -> 1
A5: 46144 | B5: 490 | C5: 226 | D5: 31 | L5: 534 | M5: =IF($A5="",0,SUMIFS(Trades!$I$4:$I$40,Trades!$D$4:$D$40,B$3,Trades!$B$4:$B$40,"<="&$A5)) -> 20 | N5: =IF($A5="",0,SUMIFS(Trades!$I$4:$I$40,Trades!$D$4:$D$40,C$3,Trades!$B$4:$B$40,"<="&$A5)) -> 15 | O5: =IF($A5="",0,SUMIFS(Trades!$I$4:$I$40,Trades!$D$4:$D$40,D$3,Trades!$B$4:$B$40,"<="&$A5)) -> 40 | P5: =IF($A5="",0,SUMIFS(Trades!$I$4:$I$40,Trades!$D$4:$D$40,E$3,Trades!$B$4:$B$40,"<="&$A5)) -> 0 | Q5: =IF($A5="",0,SUMIFS(Trades!$I$4:$I$40,Trades!$D$4:$D$40,F$3,Trades!$B$4:$B$40,"<="&$A5)) -> 0 | R5: =IF($A5="",0,SUMIFS(Trades!$I$4:$I$40,Trades!$D$4:$D$40,G$3,Trades!$B$4:$B$40,"<="&$A5)) -> 0 | S5: =IF($A5="",0,SUMIFS(Trades!$I$4:$I$40,Trades!$D$4:$D$40,H$3,Trades!$B$4:$B$40,"<="&$A5)) -> 0 | T5: =IF($A5="",0,SUMIFS(Trades!$I$4:$I$40,Trades!$D$4:$D$40,I$3,Trades!$B$4:$B$40,"<="&$A5)) -> 0 | ... V5: =IF($A5="",0,SUMIFS(Trades!$I$4:$I$40,Trades!$D$4:$D$40,K$3,Trades!$B$4:$B$40,"<="&$A5)) -> 0 | W5: =IF($A5="",0,Settings!$B$4+SUMIFS(CashEvents!$E$4:$E$30,CashEvents!$A$4:$A$30,"<="&$A5)+SUMIFS(Trades!$J$4:$J$40,Trades!$B$4:$B$40,"<="&$A5)) -> 10700 | X5: =IF($A5="","",SUMPRODUCT($B5:$K5,$M5:$V5)+$W5) -> 25130 | Y5: =IF(OR($A5="",$A4=""),"",SUMIFS(CashEvents!$E$4:$E$30,CashEvents!$A$4:$A$30,">"&$A4,CashEvents!$A$4:$A$30,"<="&$A5)) -> 0 | Z5: =IF(OR($A5="",$A4=""),"",($X5-$Y5)/$X4-1) -> 0.0031936128 | AA5: =IF(OR($A5="",$L5="",$L4=""),"",$L5/$L4-1) -> 0.011363636 | AB5: =IF($A5="","",$AB4*(1+$Z5)) -> 1.0031936 | AC5: =IF($A5="","",MAX($AB$4:$AB5)) -> 1.0031936 | AD5: =IF($A5="","",$AB5/$AC5-1) -> 0 | AE5: =IF($A5="","",$AE4*(1+$AA5)) -> 1.0113636
A6: 46160 | B6: 492 | C6: 224 | D6: 29.5 | E6: 122 | L6: 536 | M6: =IF($A6="",0,SUMIFS(Trades!$I$4:$I$40,Trades!$D$4:$D$40,B$3,Trades!$B$4:$B$40,"<="&$A6)) -> 20 | N6: =IF($A6="",0,SUMIFS(Trades!$I$4:$I$40,Trades!$D$4:$D$40,C$3,Trades!$B$4:$B$40,"<="&$A6)) -> 15 | O6: =IF($A6="",0,SUMIFS(Trades!$I$4:$I$40,Trades!$D$4:$D$40,D$3,Trades!$B$4:$B$40,"<="&$A6)) -> 0 | P6: =IF($A6="",0,SUMIFS(Trades!$I$4:$I$40,Trades!$D$4:$D$40,E$3,Trades!$B$4:$B$40,"<="&$A6)) -> 10 | Q6: =IF($A6="",0,SUMIFS(Trades!$I$4:$I$40,Trades!$D$4:$D$40,F$3,Trades!$B$4:$B$40,"<="&$A6)) -> 0 | R6: =IF($A6="",0,SUMIFS(Trades!$I$4:$I$40,Trades!$D$4:$D$40,G$3,Trades!$B$4:$B$40,"<="&$A6)) -> 0 | S6: =IF($A6="",0,SUMIFS(Trades!$I$4:$I$40,Trades!$D$4:$D$40,H$3,Trades!$B$4:$B$40,"<="&$A6)) -> 0 | T6: =IF($A6="",0,SUMIFS(Trades!$I$4:$I$40,Trades!$D$4:$D$40,I$3,Trades!$B$4:$B$40,"<="&$A6)) -> 0 | ... V6: =IF($A6="",0,SUMIFS(Trades!$I$4:$I$40,Trades!$D$4:$D$40,K$3,Trades!$B$4:$B$40,"<="&$A6)) -> 0 | W6: =IF($A6="",0,Settings!$B$4+SUMIFS(CashEvents!$E$4:$E$30,CashEvents!$A$4:$A$30,"<="&$A6)+SUMIFS(Trades!$J$4:$J$40,Trades!$B$4:$B$40,"<="&$A6)) -> 10700 | X6: =IF($A6="","",SUMPRODUCT($B6:$K6,$M6:$V6)+$W6) -> 25120 | Y6: =IF(OR($A6="",$A5=""),"",SUMIFS(CashEvents!$E$4:$E$30,CashEvents!$A$4:$A$30,">"&$A5,CashEvents!$A$4:$A$30,"<="&$A6)) -> 0 | Z6: =IF(OR($A6="",$A5=""),"",($X6-$Y6)/$X5-1) -> -0.00039793076 | AA6: =IF(OR($A6="",$L6="",$L5=""),"",$L6/$L5-1) -> 0.0037453184 | AB6: =IF($A6="","",$AB5*(1+$Z6)) -> 1.0027944 | AC6: =IF($A6="","",MAX($AB$4:$AB6)) -> 1.0031936 | AD6: =IF($A6="","",$AB6/$AC6-1) -> -0.00039793076 | AE6: =IF($A6="","",$AE5*(1+$AA6)) -> 1.0151515
A7: 46174 | B7: 498 | C7: 228 | D7: 27 | E7: 128 | L7: 542 | M7: =IF($A7="",0,SUMIFS(Trades!$I$4:$I$40,Trades!$D$4:$D$40,B$3,Trades!$B$4:$B$40,"<="&$A7)) -> 20 | N7: =IF($A7="",0,SUMIFS(Trades!$I$4:$I$40,Trades!$D$4:$D$40,C$3,Trades!$B$4:$B$40,"<="&$A7)) -> 15 | O7: =IF($A7="",0,SUMIFS(Trades!$I$4:$I$40,Trades!$D$4:$D$40,D$3,Trades!$B$4:$B$40,"<="&$A7)) -> 0 | P7: =IF($A7="",0,SUMIFS(Trades!$I$4:$I$40,Trades!$D$4:$D$40,E$3,Trades!$B$4:$B$40,"<="&$A7)) -> 10 | Q7: =IF($A7="",0,SUMIFS(Trades!$I$4:$I$40,Trades!$D$4:$D$40,F$3,Trades!$B$4:$B$40,"<="&$A7)) -> 0 | R7: =IF($A7="",0,SUMIFS(Trades!$I$4:$I$40,Trades!$D$4:$D$40,G$3,Trades!$B$4:$B$40,"<="&$A7)) -> 0 | S7: =IF($A7="",0,SUMIFS(Trades!$I$4:$I$40,Trades!$D$4:$D$40,H$3,Trades!$B$4:$B$40,"<="&$A7)) -> 0 | T7: =IF($A7="",0,SUMIFS(Trades!$I$4:$I$40,Trades!$D$4:$D$40,I$3,Trades!$B$4:$B$40,"<="&$A7)) -> 0 | ... V7: =IF($A7="",0,SUMIFS(Trades!$I$4:$I$40,Trades!$D$4:$D$40,K$3,Trades!$B$4:$B$40,"<="&$A7)) -> 0 | W7: =IF($A7="",0,Settings!$B$4+SUMIFS(CashEvents!$E$4:$E$30,CashEvents!$A$4:$A$30,"<="&$A7)+SUMIFS(Trades!$J$4:$J$40,Trades!$B$4:$B$40,"<="&$A7)) -> 13700 | X7: =IF($A7="","",SUMPRODUCT($B7:$K7,$M7:$V7)+$W7) -> 28360 | Y7: =IF(OR($A7="",$A6=""),"",SUMIFS(CashEvents!$E$4:$E$30,CashEvents!$A$4:$A$30,">"&$A6,CashEvents!$A$4:$A$30,"<="&$A7)) -> 3000 | Z7: =IF(OR($A7="",$A6=""),"",($X7-$Y7)/$X6-1) -> 0.0095541401 | AA7: =IF(OR($A7="",$L7="",$L6=""),"",$L7/$L6-1) -> 0.01119403 | AB7: =IF($A7="","",$AB6*(1+$Z7)) -> 1.0123752 | AC7: =IF($A7="","",MAX($AB$4:$AB7)) -> 1.0123752 | AD7: =IF($A7="","",$AB7/$AC7-1) -> 0 | AE7: =IF($A7="","",$AE6*(1+$AA7)) -> 1.0265152
A8: 46191 | B8: 503 | C8: 231 | D8: 25.5 | E8: 134 | F8: 424 | L8: 548 | M8: =IF($A8="",0,SUMIFS(Trades!$I$4:$I$40,Trades!$D$4:$D$40,B$3,Trades!$B$4:$B$40,"<="&$A8)) -> 20 | N8: =IF($A8="",0,SUMIFS(Trades!$I$4:$I$40,Trades!$D$4:$D$40,C$3,Trades!$B$4:$B$40,"<="&$A8)) -> 10 | O8: =IF($A8="",0,SUMIFS(Trades!$I$4:$I$40,Trades!$D$4:$D$40,D$3,Trades!$B$4:$B$40,"<="&$A8)) -> 0 | P8: =IF($A8="",0,SUMIFS(Trades!$I$4:$I$40,Trades!$D$4:$D$40,E$3,Trades!$B$4:$B$40,"<="&$A8)) -> 10 | Q8: =IF($A8="",0,SUMIFS(Trades!$I$4:$I$40,Trades!$D$4:$D$40,F$3,Trades!$B$4:$B$40,"<="&$A8)) -> 3 | R8: =IF($A8="",0,SUMIFS(Trades!$I$4:$I$40,Trades!$D$4:$D$40,G$3,Trades!$B$4:$B$40,"<="&$A8)) -> 0 | S8: =IF($A8="",0,SUMIFS(Trades!$I$4:$I$40,Trades!$D$4:$D$40,H$3,Trades!$B$4:$B$40,"<="&$A8)) -> 0 | T8: =IF($A8="",0,SUMIFS(Trades!$I$4:$I$40,Trades!$D$4:$D$40,I$3,Trades!$B$4:$B$40,"<="&$A8)) -> 0 | ... V8: =IF($A8="",0,SUMIFS(Trades!$I$4:$I$40,Trades!$D$4:$D$40,K$3,Trades!$B$4:$B$40,"<="&$A8)) -> 0 | W8: =IF($A8="",0,Settings!$B$4+SUMIFS(CashEvents!$E$4:$E$30,CashEvents!$A$4:$A$30,"<="&$A8)+SUMIFS(Trades!$J$4:$J$40,Trades!$B$4:$B$40,"<="&$A8)) -> 13590 | X8: =IF($A8="","",SUMPRODUCT($B8:$K8,$M8:$V8)+$W8) -> 28572 | Y8: =IF(OR($A8="",$A7=""),"",SUMIFS(CashEvents!$E$4:$E$30,CashEvents!$A$4:$A$30,">"&$A7,CashEvents!$A$4:$A$30,"<="&$A8)) -> 0 | Z8: =IF(OR($A8="",$A7=""),"",($X8-$Y8)/$X7-1) -> 0.0074753173 | AA8: =IF(OR($A8="",$L8="",$L7=""),"",$L8/$L7-1) -> 0.011070111 | AB8: =IF($A8="","",$AB7*(1+$Z8)) -> 1.0199431 | AC8: =IF($A8="","",MAX($AB$4:$AB8)) -> 1.0199431 | AD8: =IF($A8="","",$AB8/$AC8-1) -> 0 | AE8: =IF($A8="","",$AE7*(1+$AA8)) -> 1.0378788
A9: 46197 | B9: 507 | C9: 233 | D9: 24.8 | E9: 138 | F9: 428 | L9: 552 | M9: =IF($A9="",0,SUMIFS(Trades!$I$4:$I$40,Trades!$D$4:$D$40,B$3,Trades!$B$4:$B$40,"<="&$A9)) -> 20 | N9: =IF($A9="",0,SUMIFS(Trades!$I$4:$I$40,Trades!$D$4:$D$40,C$3,Trades!$B$4:$B$40,"<="&$A9)) -> 10 | O9: =IF($A9="",0,SUMIFS(Trades!$I$4:$I$40,Trades!$D$4:$D$40,D$3,Trades!$B$4:$B$40,"<="&$A9)) -> 0 | P9: =IF($A9="",0,SUMIFS(Trades!$I$4:$I$40,Trades!$D$4:$D$40,E$3,Trades!$B$4:$B$40,"<="&$A9)) -> 10 | Q9: =IF($A9="",0,SUMIFS(Trades!$I$4:$I$40,Trades!$D$4:$D$40,F$3,Trades!$B$4:$B$40,"<="&$A9)) -> 3 | R9: =IF($A9="",0,SUMIFS(Trades!$I$4:$I$40,Trades!$D$4:$D$40,G$3,Trades!$B$4:$B$40,"<="&$A9)) -> 0 | S9: =IF($A9="",0,SUMIFS(Trades!$I$4:$I$40,Trades!$D$4:$D$40,H$3,Trades!$B$4:$B$40,"<="&$A9)) -> 0 | T9: =IF($A9="",0,SUMIFS(Trades!$I$4:$I$40,Trades!$D$4:$D$40,I$3,Trades!$B$4:$B$40,"<="&$A9)) -> 0 | ... V9: =IF($A9="",0,SUMIFS(Trades!$I$4:$I$40,Trades!$D$4:$D$40,K$3,Trades!$B$4:$B$40,"<="&$A9)) -> 0 | W9: =IF($A9="",0,Settings!$B$4+SUMIFS(CashEvents!$E$4:$E$30,CashEvents!$A$4:$A$30,"<="&$A9)+SUMIFS(Trades!$J$4:$J$40,Trades!$B$4:$B$40,"<="&$A9)) -> 13590 | X9: =IF($A9="","",SUMPRODUCT($B9:$K9,$M9:$V9)+$W9) -> 28724 | Y9: =IF(OR($A9="",$A8=""),"",SUMIFS(CashEvents!$E$4:$E$30,CashEvents!$A$4:$A$30,">"&$A8,CashEvents!$A$4:$A$30,"<="&$A9)) -> 0 | Z9: =IF(OR($A9="",$A8=""),"",($X9-$Y9)/$X8-1) -> 0.0053198936 | AA9: =IF(OR($A9="",$L9="",$L8=""),"",$L9/$L8-1) -> 0.0072992701 | AB9: =IF($A9="","",$AB8*(1+$Z9)) -> 1.0253691 | AC9: =IF($A9="","",MAX($AB$4:$AB9)) -> 1.0253691 | AD9: =IF($A9="","",$AB9/$AC9-1) -> 0 | AE9: =IF($A9="","",$AE8*(1+$AA9)) -> 1.0454545
A10: 46203 | B10: 510 | C10: 235 | D10: 24 | E10: 141 | F10: 432 | L10: 555 | M10: =IF($A10="",0,SUMIFS(Trades!$I$4:$I$40,Trades!$D$4:$D$40,B$3,Trades!$B$4:$B$40,"<="&$A10)) -> 20 | N10: =IF($A10="",0,SUMIFS(Trades!$I$4:$I$40,Trades!$D$4:$D$40,C$3,Trades!$B$4:$B$40,"<="&$A10)) -> 10 | O10: =IF($A10="",0,SUMIFS(Trades!$I$4:$I$40,Trades!$D$4:$D$40,D$3,Trades!$B$4:$B$40,"<="&$A10)) -> 0 | P10: =IF($A10="",0,SUMIFS(Trades!$I$4:$I$40,Trades!$D$4:$D$40,E$3,Trades!$B$4:$B$40,"<="&$A10)) -> 10 | Q10: =IF($A10="",0,SUMIFS(Trades!$I$4:$I$40,Trades!$D$4:$D$40,F$3,Trades!$B$4:$B$40,"<="&$A10)) -> 3 | R10: =IF($A10="",0,SUMIFS(Trades!$I$4:$I$40,Trades!$D$4:$D$40,G$3,Trades!$B$4:$B$40,"<="&$A10)) -> 0 | S10: =IF($A10="",0,SUMIFS(Trades!$I$4:$I$40,Trades!$D$4:$D$40,H$3,Trades!$B$4:$B$40,"<="&$A10)) -> 0 | T10: =IF($A10="",0,SUMIFS(Trades!$I$4:$I$40,Trades!$D$4:$D$40,I$3,Trades!$B$4:$B$40,"<="&$A10)) -> 0 | ... V10: =IF($A10="",0,SUMIFS(Trades!$I$4:$I$40,Trades!$D$4:$D$40,K$3,Trades!$B$4:$B$40,"<="&$A10)) -> 0 | W10: =IF($A10="",0,Settings!$B$4+SUMIFS(CashEvents!$E$4:$E$30,CashEvents!$A$4:$A$30,"<="&$A10)+SUMIFS(Trades!$J$4:$J$40,Trades!$B$4:$B$40,"<="&$A10)) -> 13590 | X10: =IF($A10="","",SUMPRODUCT($B10:$K10,$M10:$V10)+$W10) -> 28846 | Y10: =IF(OR($A10="",$A9=""),"",SUMIFS(CashEvents!$E$4:$E$30,CashEvents!$A$4:$A$30,">"&$A9,CashEvents!$A$4:$A$30,"<="&$A10)) -> 0 | Z10: =IF(OR($A10="",$A9=""),"",($X10-$Y10)/$X9-1) -> 0.0042473193 | AA10: =IF(OR($A10="",$L10="",$L9=""),"",$L10/$L9-1) -> 0.0054347826 | AB10: =IF($A10="","",$AB9*(1+$Z10)) -> 1.0297241 | AC10: =IF($A10="","",MAX($AB$4:$AB10)) -> 1.0297241 | AD10: =IF($A10="","",$AB10/$AC10-1) -> 0 | AE10: =IF($A10="","",$AE9*(1+$AA10)) -> 1.0511364
M11: =IF($A11="",0,SUMIFS(Trades!$I$4:$I$40,Trades!$D$4:$D$40,B$3,Trades!$B$4:$B$40,"<="&$A11)) -> 0 | N11: =IF($A11="",0,SUMIFS(Trades!$I$4:$I$40,Trades!$D$4:$D$40,C$3,Trades!$B$4:$B$40,"<="&$A11)) -> 0 | O11: =IF($A11="",0,SUMIFS(Trades!$I$4:$I$40,Trades!$D$4:$D$40,D$3,Trades!$B$4:$B$40,"<="&$A11)) -> 0 | P11: =IF($A11="",0,SUMIFS(Trades!$I$4:$I$40,Trades!$D$4:$D$40,E$3,Trades!$B$4:$B$40,"<="&$A11)) -> 0 | Q11: =IF($A11="",0,SUMIFS(Trades!$I$4:$I$40,Trades!$D$4:$D$40,F$3,Trades!$B$4:$B$40,"<="&$A11)) -> 0 | R11: =IF($A11="",0,SUMIFS(Trades!$I$4:$I$40,Trades!$D$4:$D$40,G$3,Trades!$B$4:$B$40,"<="&$A11)) -> 0 | S11: =IF($A11="",0,SUMIFS(Trades!$I$4:$I$40,Trades!$D$4:$D$40,H$3,Trades!$B$4:$B$40,"<="&$A11)) -> 0 | T11: =IF($A11="",0,SUMIFS(Trades!$I$4:$I$40,Trades!$D$4:$D$40,I$3,Trades!$B$4:$B$40,"<="&$A11)) -> 0 | ... V11: =IF($A11="",0,SUMIFS(Trades!$I$4:$I$40,Trades!$D$4:$D$40,K$3,Trades!$B$4:$B$40,"<="&$A11)) -> 0 | W11: =IF($A11="",0,Settings!$B$4+SUMIFS(CashEvents!$E$4:$E$30,CashEvents!$A$4:$A$30,"<="&$A11)+SUMIFS(Trades!$J$4:$J$40,Trades!$B$4:$B$40,"<="&$A11)) -> 0 | X11: =IF($A11="","",SUMPRODUCT($B11:$K11,$M11:$V11)+$W11) | Y11: =IF(OR($A11="",$A10=""),"",SUMIFS(CashEvents!$E$4:$E$30,CashEvents!$A$4:$A$30,">"&$A10,CashEvents!$A$4:$A$30,"<="&$A11)) | Z11: =IF(OR($A11="",$A10=""),"",($X11-$Y11)/$X10-1) | AA11: =IF(OR($A11="",$L11="",$L10=""),"",$L11/$L10-1) | AB11: =IF($A11="","",$AB10*(1+$Z11)) | AC11: =IF($A11="","",MAX($AB$4:$AB11)) | AD11: =IF($A11="","",$AB11/$AC11-1) | AE11: =IF($A11="","",$AE10*(1+$AA11))
M12: =IF($A12="",0,SUMIFS(Trades!$I$4:$I$40,Trades!$D$4:$D$40,B$3,Trades!$B$4:$B$40,"<="&$A12)) -> 0 | N12: =IF($A12="",0,SUMIFS(Trades!$I$4:$I$40,Trades!$D$4:$D$40,C$3,Trades!$B$4:$B$40,"<="&$A12)) -> 0 | O12: =IF($A12="",0,SUMIFS(Trades!$I$4:$I$40,Trades!$D$4:$D$40,D$3,Trades!$B$4:$B$40,"<="&$A12)) -> 0 | P12: =IF($A12="",0,SUMIFS(Trades!$I$4:$I$40,Trades!$D$4:$D$40,E$3,Trades!$B$4:$B$40,"<="&$A12)) -> 0 | Q12: =IF($A12="",0,SUMIFS(Trades!$I$4:$I$40,Trades!$D$4:$D$40,F$3,Trades!$B$4:$B$40,"<="&$A12)) -> 0 | R12: =IF($A12="",0,SUMIFS(Trades!$I$4:$I$40,Trades!$D$4:$D$40,G$3,Trades!$B$4:$B$40,"<="&$A12)) -> 0 | S12: =IF($A12="",0,SUMIFS(Trades!$I$4:$I$40,Trades!$D$4:$D$40,H$3,Trades!$B$4:$B$40,"<="&$A12)) -> 0 | T12: =IF($A12="",0,SUMIFS(Trades!$I$4:$I$40,Trades!$D$4:$D$40,I$3,Trades!$B$4:$B$40,"<="&$A12)) -> 0 | ... V12: =IF($A12="",0,SUMIFS(Trades!$I$4:$I$40,Trades!$D$4:$D$40,K$3,Trades!$B$4:$B$40,"<="&$A12)) -> 0 | W12: =IF($A12="",0,Settings!$B$4+SUMIFS(CashEvents!$E$4:$E$30,CashEvents!$A$4:$A$30,"<="&$A12)+SUMIFS(Trades!$J$4:$J$40,Trades!$B$4:$B$40,"<="&$A12)) -> 0 | X12: =IF($A12="","",SUMPRODUCT($B12:$K12,$M12:$V12)+$W12) | Y12: =IF(OR($A12="",$A11=""),"",SUMIFS(CashEvents!$E$4:$E$30,CashEvents!$A$4:$A$30,">"&$A11,CashEvents!$A$4:$A$30,"<="&$A12)) | Z12: =IF(OR($A12="",$A11=""),"",($X12-$Y12)/$X11-1) | AA12: =IF(OR($A12="",$L12="",$L11=""),"",$L12/$L11-1) | AB12: =IF($A12="","",$AB11*(1+$Z12)) | AC12: =IF($A12="","",MAX($AB$4:$AB12)) | AD12: =IF($A12="","",$AB12/$AC12-1) | AE12: =IF($A12="","",$AE11*(1+$AA12))
M13: =IF($A13="",0,SUMIFS(Trades!$I$4:$I$40,Trades!$D$4:$D$40,B$3,Trades!$B$4:$B$40,"<="&$A13)) -> 0 | N13: =IF($A13="",0,SUMIFS(Trades!$I$4:$I$40,Trades!$D$4:$D$40,C$3,Trades!$B$4:$B$40,"<="&$A13)) -> 0 | O13: =IF($A13="",0,SUMIFS(Trades!$I$4:$I$40,Trades!$D$4:$D$40,D$3,Trades!$B$4:$B$40,"<="&$A13)) -> 0 | P13: =IF($A13="",0,SUMIFS(Trades!$I$4:$I$40,Trades!$D$4:$D$40,E$3,Trades!$B$4:$B$40,"<="&$A13)) -> 0 | Q13: =IF($A13="",0,SUMIFS(Trades!$I$4:$I$40,Trades!$D$4:$D$40,F$3,Trades!$B$4:$B$40,"<="&$A13)) -> 0 | R13: =IF($A13="",0,SUMIFS(Trades!$I$4:$I$40,Trades!$D$4:$D$40,G$3,Trades!$B$4:$B$40,"<="&$A13)) -> 0 | S13: =IF($A13="",0,SUMIFS(Trades!$I$4:$I$40,Trades!$D$4:$D$40,H$3,Trades!$B$4:$B$40,"<="&$A13)) -> 0 | T13: =IF($A13="",0,SUMIFS(Trades!$I$4:$I$40,Trades!$D$4:$D$40,I$3,Trades!$B$4:$B$40,"<="&$A13)) -> 0 | ... V13: =IF($A13="",0,SUMIFS(Trades!$I$4:$I$40,Trades!$D$4:$D$40,K$3,Trades!$B$4:$B$40,"<="&$A13)) -> 0 | W13: =IF($A13="",0,Settings!$B$4+SUMIFS(CashEvents!$E$4:$E$30,CashEvents!$A$4:$A$30,"<="&$A13)+SUMIFS(Trades!$J$4:$J$40,Trades!$B$4:$B$40,"<="&$A13)) -> 0 | X13: =IF($A13="","",SUMPRODUCT($B13:$K13,$M13:$V13)+$W13) | Y13: =IF(OR($A13="",$A12=""),"",SUMIFS(CashEvents!$E$4:$E$30,CashEvents!$A$4:$A$30,">"&$A12,CashEvents!$A$4:$A$30,"<="&$A13)) | Z13: =IF(OR($A13="",$A12=""),"",($X13-$Y13)/$X12-1) | AA13: =IF(OR($A13="",$L13="",$L12=""),"",$L13/$L12-1) | AB13: =IF($A13="","",$AB12*(1+$Z13)) | AC13: =IF($A13="","",MAX($AB$4:$AB13)) | AD13: =IF($A13="","",$AB13/$AC13-1) | AE13: =IF($A13="","",$AE12*(1+$AA13))
M14: =IF($A14="",0,SUMIFS(Trades!$I$4:$I$40,Trades!$D$4:$D$40,B$3,Trades!$B$4:$B$40,"<="&$A14)) -> 0 | N14: =IF($A14="",0,SUMIFS(Trades!$I$4:$I$40,Trades!$D$4:$D$40,C$3,Trades!$B$4:$B$40,"<="&$A14)) -> 0 | O14: =IF($A14="",0,SUMIFS(Trades!$I$4:$I$40,Trades!$D$4:$D$40,D$3,Trades!$B$4:$B$40,"<="&$A14)) -> 0 | P14: =IF($A14="",0,SUMIFS(Trades!$I$4:$I$40,Trades!$D$4:$D$40,E$3,Trades!$B$4:$B$40,"<="&$A14)) -> 0 | Q14: =IF($A14="",0,SUMIFS(Trades!$I$4:$I$40,Trades!$D$4:$D$40,F$3,Trades!$B$4:$B$40,"<="&$A14)) -> 0 | R14: =IF($A14="",0,SUMIFS(Trades!$I$4:$I$40,Trades!$D$4:$D$40,G$3,Trades!$B$4:$B$40,"<="&$A14)) -> 0 | S14: =IF($A14="",0,SUMIFS(Trades!$I$4:$I$40,Trades!$D$4:$D$40,H$3,Trades!$B$4:$B$40,"<="&$A14)) -> 0 | T14: =IF($A14="",0,SUMIFS(Trades!$I$4:$I$40,Trades!$D$4:$D$40,I$3,Trades!$B$4:$B$40,"<="&$A14)) -> 0 | ... V14: =IF($A14="",0,SUMIFS(Trades!$I$4:$I$40,Trades!$D$4:$D$40,K$3,Trades!$B$4:$B$40,"<="&$A14)) -> 0 | W14: =IF($A14="",0,Settings!$B$4+SUMIFS(CashEvents!$E$4:$E$30,CashEvents!$A$4:$A$30,"<="&$A14)+SUMIFS(Trades!$J$4:$J$40,Trades!$B$4:$B$40,"<="&$A14)) -> 0 | X14: =IF($A14="","",SUMPRODUCT($B14:$K14,$M14:$V14)+$W14) | Y14: =IF(OR($A14="",$A13=""),"",SUMIFS(CashEvents!$E$4:$E$30,CashEvents!$A$4:$A$30,">"&$A13,CashEvents!$A$4:$A$30,"<="&$A14)) | Z14: =IF(OR($A14="",$A13=""),"",($X14-$Y14)/$X13-1) | AA14: =IF(OR($A14="",$L14="",$L13=""),"",$L14/$L13-1) | AB14: =IF($A14="","",$AB13*(1+$Z14)) | AC14: =IF($A14="","",MAX($AB$4:$AB14)) | AD14: =IF($A14="","",$AB14/$AC14-1) | AE14: =IF($A14="","",$AE13*(1+$AA14))
M15: =IF($A15="",0,SUMIFS(Trades!$I$4:$I$40,Trades!$D$4:$D$40,B$3,Trades!$B$4:$B$40,"<="&$A15)) -> 0 | N15: =IF($A15="",0,SUMIFS(Trades!$I$4:$I$40,Trades!$D$4:$D$40,C$3,Trades!$B$4:$B$40,"<="&$A15)) -> 0 | O15: =IF($A15="",0,SUMIFS(Trades!$I$4:$I$40,Trades!$D$4:$D$40,D$3,Trades!$B$4:$B$40,"<="&$A15)) -> 0 | P15: =IF($A15="",0,SUMIFS(Trades!$I$4:$I$40,Trades!$D$4:$D$40,E$3,Trades!$B$4:$B$40,"<="&$A15)) -> 0 | Q15: =IF($A15="",0,SUMIFS(Trades!$I$4:$I$40,Trades!$D$4:$D$40,F$3,Trades!$B$4:$B$40,"<="&$A15)) -> 0 | R15: =IF($A15="",0,SUMIFS(Trades!$I$4:$I$40,Trades!$D$4:$D$40,G$3,Trades!$B$4:$B$40,"<="&$A15)) -> 0 | S15: =IF($A15="",0,SUMIFS(Trades!$I$4:$I$40,Trades!$D$4:$D$40,H$3,Trades!$B$4:$B$40,"<="&$A15)) -> 0 | T15: =IF($A15="",0,SUMIFS(Trades!$I$4:$I$40,Trades!$D$4:$D$40,I$3,Trades!$B$4:$B$40,"<="&$A15)) -> 0 | ... V15: =IF($A15="",0,SUMIFS(Trades!$I$4:$I$40,Trades!$D$4:$D$40,K$3,Trades!$B$4:$B$40,"<="&$A15)) -> 0 | W15: =IF($A15="",0,Settings!$B$4+SUMIFS(CashEvents!$E$4:$E$30,CashEvents!$A$4:$A$30,"<="&$A15)+SUMIFS(Trades!$J$4:$J$40,Trades!$B$4:$B$40,"<="&$A15)) -> 0 | X15: =IF($A15="","",SUMPRODUCT($B15:$K15,$M15:$V15)+$W15) | Y15: =IF(OR($A15="",$A14=""),"",SUMIFS(CashEvents!$E$4:$E$30,CashEvents!$A$4:$A$30,">"&$A14,CashEvents!$A$4:$A$30,"<="&$A15)) | Z15: =IF(OR($A15="",$A14=""),"",($X15-$Y15)/$X14-1) | AA15: =IF(OR($A15="",$L15="",$L14=""),"",$L15/$L14-1) | AB15: =IF($A15="","",$AB14*(1+$Z15)) | AC15: =IF($A15="","",MAX($AB$4:$AB15)) | AD15: =IF($A15="","",$AB15/$AC15-1) | AE15: =IF($A15="","",$AE14*(1+$AA15))
M16: =IF($A16="",0,SUMIFS(Trades!$I$4:$I$40,Trades!$D$4:$D$40,B$3,Trades!$B$4:$B$40,"<="&$A16)) -> 0 | N16: =IF($A16="",0,SUMIFS(Trades!$I$4:$I$40,Trades!$D$4:$D$40,C$3,Trades!$B$4:$B$40,"<="&$A16)) -> 0 | O16: =IF($A16="",0,SUMIFS(Trades!$I$4:$I$40,Trades!$D$4:$D$40,D$3,Trades!$B$4:$B$40,"<="&$A16)) -> 0 | P16: =IF($A16="",0,SUMIFS(Trades!$I$4:$I$40,Trades!$D$4:$D$40,E$3,Trades!$B$4:$B$40,"<="&$A16)) -> 0 | Q16: =IF($A16="",0,SUMIFS(Trades!$I$4:$I$40,Trades!$D$4:$D$40,F$3,Trades!$B$4:$B$40,"<="&$A16)) -> 0 | R16: =IF($A16="",0,SUMIFS(Trades!$I$4:$I$40,Trades!$D$4:$D$40,G$3,Trades!$B$4:$B$40,"<="&$A16)) -> 0 | S16: =IF($A16="",0,SUMIFS(Trades!$I$4:$I$40,Trades!$D$4:$D$40,H$3,Trades!$B$4:$B$40,"<="&$A16)) -> 0 | T16: =IF($A16="",0,SUMIFS(Trades!$I$4:$I$40,Trades!$D$4:$D$40,I$3,Trades!$B$4:$B$40,"<="&$A16)) -> 0 | ... V16: =IF($A16="",0,SUMIFS(Trades!$I$4:$I$40,Trades!$D$4:$D$40,K$3,Trades!$B$4:$B$40,"<="&$A16)) -> 0 | W16: =IF($A16="",0,Settings!$B$4+SUMIFS(CashEvents!$E$4:$E$30,CashEvents!$A$4:$A$30,"<="&$A16)+SUMIFS(Trades!$J$4:$J$40,Trades!$B$4:$B$40,"<="&$A16)) -> 0 | X16: =IF($A16="","",SUMPRODUCT($B16:$K16,$M16:$V16)+$W16) | Y16: =IF(OR($A16="",$A15=""),"",SUMIFS(CashEvents!$E$4:$E$30,CashEvents!$A$4:$A$30,">"&$A15,CashEvents!$A$4:$A$30,"<="&$A16)) | Z16: =IF(OR($A16="",$A15=""),"",($X16-$Y16)/$X15-1) | AA16: =IF(OR($A16="",$L16="",$L15=""),"",$L16/$L15-1) | AB16: =IF($A16="","",$AB15*(1+$Z16)) | AC16: =IF($A16="","",MAX($AB$4:$AB16)) | AD16: =IF($A16="","",$AB16/$AC16-1) | AE16: =IF($A16="","",$AE15*(1+$AA16))
M17: =IF($A17="",0,SUMIFS(Trades!$I$4:$I$40,Trades!$D$4:$D$40,B$3,Trades!$B$4:$B$40,"<="&$A17)) -> 0 | N17: =IF($A17="",0,SUMIFS(Trades!$I$4:$I$40,Trades!$D$4:$D$40,C$3,Trades!$B$4:$B$40,"<="&$A17)) -> 0 | O17: =IF($A17="",0,SUMIFS(Trades!$I$4:$I$40,Trades!$D$4:$D$40,D$3,Trades!$B$4:$B$40,"<="&$A17)) -> 0 | P17: =IF($A17="",0,SUMIFS(Trades!$I$4:$I$40,Trades!$D$4:$D$40,E$3,Trades!$B$4:$B$40,"<="&$A17)) -> 0 | Q17: =IF($A17="",0,SUMIFS(Trades!$I$4:$I$40,Trades!$D$4:$D$40,F$3,Trades!$B$4:$B$40,"<="&$A17)) -> 0 | R17: =IF($A17="",0,SUMIFS(Trades!$I$4:$I$40,Trades!$D$4:$D$40,G$3,Trades!$B$4:$B$40,"<="&$A17)) -> 0 | S17: =IF($A17="",0,SUMIFS(Trades!$I$4:$I$40,Trades!$D$4:$D$40,H$3,Trades!$B$4:$B$40,"<="&$A17)) -> 0 | T17: =IF($A17="",0,SUMIFS(Trades!$I$4:$I$40,Trades!$D$4:$D$40,I$3,Trades!$B$4:$B$40,"<="&$A17)) -> 0 | ... V17: =IF($A17="",0,SUMIFS(Trades!$I$4:$I$40,Trades!$D$4:$D$40,K$3,Trades!$B$4:$B$40,"<="&$A17)) -> 0 | W17: =IF($A17="",0,Settings!$B$4+SUMIFS(CashEvents!$E$4:$E$30,CashEvents!$A$4:$A$30,"<="&$A17)+SUMIFS(Trades!$J$4:$J$40,Trades!$B$4:$B$40,"<="&$A17)) -> 0 | X17: =IF($A17="","",SUMPRODUCT($B17:$K17,$M17:$V17)+$W17) | Y17: =IF(OR($A17="",$A16=""),"",SUMIFS(CashEvents!$E$4:$E$30,CashEvents!$A$4:$A$30,">"&$A16,CashEvents!$A$4:$A$30,"<="&$A17)) | Z17: =IF(OR($A17="",$A16=""),"",($X17-$Y17)/$X16-1) | AA17: =IF(OR($A17="",$L17="",$L16=""),"",$L17/$L16-1) | AB17: =IF($A17="","",$AB16*(1+$Z17)) | AC17: =IF($A17="","",MAX($AB$4:$AB17)) | AD17: =IF($A17="","",$AB17/$AC17-1) | AE17: =IF($A17="","",$AE16*(1+$AA17))
M18: =IF($A18="",0,SUMIFS(Trades!$I$4:$I$40,Trades!$D$4:$D$40,B$3,Trades!$B$4:$B$40,"<="&$A18)) -> 0 | N18: =IF($A18="",0,SUMIFS(Trades!$I$4:$I$40,Trades!$D$4:$D$40,C$3,Trades!$B$4:$B$40,"<="&$A18)) -> 0 | O18: =IF($A18="",0,SUMIFS(Trades!$I$4:$I$40,Trades!$D$4:$D$40,D$3,Trades!$B$4:$B$40,"<="&$A18)) -> 0 | P18: =IF($A18="",0,SUMIFS(Trades!$I$4:$I$40,Trades!$D$4:$D$40,E$3,Trades!$B$4:$B$40,"<="&$A18)) -> 0 | Q18: =IF($A18="",0,SUMIFS(Trades!$I$4:$I$40,Trades!$D$4:$D$40,F$3,Trades!$B$4:$B$40,"<="&$A18)) -> 0 | R18: =IF($A18="",0,SUMIFS(Trades!$I$4:$I$40,Trades!$D$4:$D$40,G$3,Trades!$B$4:$B$40,"<="&$A18)) -> 0 | S18: =IF($A18="",0,SUMIFS(Trades!$I$4:$I$40,Trades!$D$4:$D$40,H$3,Trades!$B$4:$B$40,"<="&$A18)) -> 0 | T18: =IF($A18="",0,SUMIFS(Trades!$I$4:$I$40,Trades!$D$4:$D$40,I$3,Trades!$B$4:$B$40,"<="&$A18)) -> 0 | ... V18: =IF($A18="",0,SUMIFS(Trades!$I$4:$I$40,Trades!$D$4:$D$40,K$3,Trades!$B$4:$B$40,"<="&$A18)) -> 0 | W18: =IF($A18="",0,Settings!$B$4+SUMIFS(CashEvents!$E$4:$E$30,CashEvents!$A$4:$A$30,"<="&$A18)+SUMIFS(Trades!$J$4:$J$40,Trades!$B$4:$B$40,"<="&$A18)) -> 0 | X18: =IF($A18="","",SUMPRODUCT($B18:$K18,$M18:$V18)+$W18) | Y18: =IF(OR($A18="",$A17=""),"",SUMIFS(CashEvents!$E$4:$E$30,CashEvents!$A$4:$A$30,">"&$A17,CashEvents!$A$4:$A$30,"<="&$A18)) | Z18: =IF(OR($A18="",$A17=""),"",($X18-$Y18)/$X17-1) | AA18: =IF(OR($A18="",$L18="",$L17=""),"",$L18/$L17-1) | AB18: =IF($A18="","",$AB17*(1+$Z18)) | AC18: =IF($A18="","",MAX($AB$4:$AB18)) | AD18: =IF($A18="","",$AB18/$AC18-1) | AE18: =IF($A18="","",$AE17*(1+$AA18))
M19: =IF($A19="",0,SUMIFS(Trades!$I$4:$I$40,Trades!$D$4:$D$40,B$3,Trades!$B$4:$B$40,"<="&$A19)) -> 0 | N19: =IF($A19="",0,SUMIFS(Trades!$I$4:$I$40,Trades!$D$4:$D$40,C$3,Trades!$B$4:$B$40,"<="&$A19)) -> 0 | O19: =IF($A19="",0,SUMIFS(Trades!$I$4:$I$40,Trades!$D$4:$D$40,D$3,Trades!$B$4:$B$40,"<="&$A19)) -> 0 | P19: =IF($A19="",0,SUMIFS(Trades!$I$4:$I$40,Trades!$D$4:$D$40,E$3,Trades!$B$4:$B$40,"<="&$A19)) -> 0 | Q19: =IF($A19="",0,SUMIFS(Trades!$I$4:$I$40,Trades!$D$4:$D$40,F$3,Trades!$B$4:$B$40,"<="&$A19)) -> 0 | R19: =IF($A19="",0,SUMIFS(Trades!$I$4:$I$40,Trades!$D$4:$D$40,G$3,Trades!$B$4:$B$40,"<="&$A19)) -> 0 | S19: =IF($A19="",0,SUMIFS(Trades!$I$4:$I$40,Trades!$D$4:$D$40,H$3,Trades!$B$4:$B$40,"<="&$A19)) -> 0 | T19: =IF($A19="",0,SUMIFS(Trades!$I$4:$I$40,Trades!$D$4:$D$40,I$3,Trades!$B$4:$B$40,"<="&$A19)) -> 0 | ... V19: =IF($A19="",0,SUMIFS(Trades!$I$4:$I$40,Trades!$D$4:$D$40,K$3,Trades!$B$4:$B$40,"<="&$A19)) -> 0 | W19: =IF($A19="",0,Settings!$B$4+SUMIFS(CashEvents!$E$4:$E$30,CashEvents!$A$4:$A$30,"<="&$A19)+SUMIFS(Trades!$J$4:$J$40,Trades!$B$4:$B$40,"<="&$A19)) -> 0 | X19: =IF($A19="","",SUMPRODUCT($B19:$K19,$M19:$V19)+$W19) | Y19: =IF(OR($A19="",$A18=""),"",SUMIFS(CashEvents!$E$4:$E$30,CashEvents!$A$4:$A$30,">"&$A18,CashEvents!$A$4:$A$30,"<="&$A19)) | Z19: =IF(OR($A19="",$A18=""),"",($X19-$Y19)/$X18-1) | AA19: =IF(OR($A19="",$L19="",$L18=""),"",$L19/$L18-1) | AB19: =IF($A19="","",$AB18*(1+$Z19)) | AC19: =IF($A19="","",MAX($AB$4:$AB19)) | AD19: =IF($A19="","",$AB19/$AC19-1) | AE19: =IF($A19="","",$AE18*(1+$AA19))
M20: =IF($A20="",0,SUMIFS(Trades!$I$4:$I$40,Trades!$D$4:$D$40,B$3,Trades!$B$4:$B$40,"<="&$A20)) -> 0 | N20: =IF($A20="",0,SUMIFS(Trades!$I$4:$I$40,Trades!$D$4:$D$40,C$3,Trades!$B$4:$B$40,"<="&$A20)) -> 0 | O20: =IF($A20="",0,SUMIFS(Trades!$I$4:$I$40,Trades!$D$4:$D$40,D$3,Trades!$B$4:$B$40,"<="&$A20)) -> 0 | P20: =IF($A20="",0,SUMIFS(Trades!$I$4:$I$40,Trades!$D$4:$D$40,E$3,Trades!$B$4:$B$40,"<="&$A20)) -> 0 | Q20: =IF($A20="",0,SUMIFS(Trades!$I$4:$I$40,Trades!$D$4:$D$40,F$3,Trades!$B$4:$B$40,"<="&$A20)) -> 0 | R20: =IF($A20="",0,SUMIFS(Trades!$I$4:$I$40,Trades!$D$4:$D$40,G$3,Trades!$B$4:$B$40,"<="&$A20)) -> 0 | S20: =IF($A20="",0,SUMIFS(Trades!$I$4:$I$40,Trades!$D$4:$D$40,H$3,Trades!$B$4:$B$40,"<="&$A20)) -> 0 | T20: =IF($A20="",0,SUMIFS(Trades!$I$4:$I$40,Trades!$D$4:$D$40,I$3,Trades!$B$4:$B$40,"<="&$A20)) -> 0 | ... V20: =IF($A20="",0,SUMIFS(Trades!$I$4:$I$40,Trades!$D$4:$D$40,K$3,Trades!$B$4:$B$40,"<="&$A20)) -> 0 | W20: =IF($A20="",0,Settings!$B$4+SUMIFS(CashEvents!$E$4:$E$30,CashEvents!$A$4:$A$30,"<="&$A20)+SUMIFS(Trades!$J$4:$J$40,Trades!$B$4:$B$40,"<="&$A20)) -> 0 | X20: =IF($A20="","",SUMPRODUCT($B20:$K20,$M20:$V20)+$W20) | Y20: =IF(OR($A20="",$A19=""),"",SUMIFS(CashEvents!$E$4:$E$30,CashEvents!$A$4:$A$30,">"&$A19,CashEvents!$A$4:$A$30,"<="&$A20)) | Z20: =IF(OR($A20="",$A19=""),"",($X20-$Y20)/$X19-1) | AA20: =IF(OR($A20="",$L20="",$L19=""),"",$L20/$L19-1) | AB20: =IF($A20="","",$AB19*(1+$Z20)) | AC20: =IF($A20="","",MAX($AB$4:$AB20)) | AD20: =IF($A20="","",$AB20/$AC20-1) | AE20: =IF($A20="","",$AE19*(1+$AA20))
M21: =IF($A21="",0,SUMIFS(Trades!$I$4:$I$40,Trades!$D$4:$D$40,B$3,Trades!$B$4:$B$40,"<="&$A21)) -> 0 | N21: =IF($A21="",0,SUMIFS(Trades!$I$4:$I$40,Trades!$D$4:$D$40,C$3,Trades!$B$4:$B$40,"<="&$A21)) -> 0 | O21: =IF($A21="",0,SUMIFS(Trades!$I$4:$I$40,Trades!$D$4:$D$40,D$3,Trades!$B$4:$B$40,"<="&$A21)) -> 0 | P21: =IF($A21="",0,SUMIFS(Trades!$I$4:$I$40,Trades!$D$4:$D$40,E$3,Trades!$B$4:$B$40,"<="&$A21)) -> 0 | Q21: =IF($A21="",0,SUMIFS(Trades!$I$4:$I$40,Trades!$D$4:$D$40,F$3,Trades!$B$4:$B$40,"<="&$A21)) -> 0 | R21: =IF($A21="",0,SUMIFS(Trades!$I$4:$I$40,Trades!$D$4:$D$40,G$3,Trades!$B$4:$B$40,"<="&$A21)) -> 0 | S21: =IF($A21="",0,SUMIFS(Trades!$I$4:$I$40,Trades!$D$4:$D$40,H$3,Trades!$B$4:$B$40,"<="&$A21)) -> 0 | T21: =IF($A21="",0,SUMIFS(Trades!$I$4:$I$40,Trades!$D$4:$D$40,I$3,Trades!$B$4:$B$40,"<="&$A21)) -> 0 | ... V21: =IF($A21="",0,SUMIFS(Trades!$I$4:$I$40,Trades!$D$4:$D$40,K$3,Trades!$B$4:$B$40,"<="&$A21)) -> 0 | W21: =IF($A21="",0,Settings!$B$4+SUMIFS(CashEvents!$E$4:$E$30,CashEvents!$A$4:$A$30,"<="&$A21)+SUMIFS(Trades!$J$4:$J$40,Trades!$B$4:$B$40,"<="&$A21)) -> 0 | X21: =IF($A21="","",SUMPRODUCT($B21:$K21,$M21:$V21)+$W21) | Y21: =IF(OR($A21="",$A20=""),"",SUMIFS(CashEvents!$E$4:$E$30,CashEvents!$A$4:$A$30,">"&$A20,CashEvents!$A$4:$A$30,"<="&$A21)) | Z21: =IF(OR($A21="",$A20=""),"",($X21-$Y21)/$X20-1) | AA21: =IF(OR($A21="",$L21="",$L20=""),"",$L21/$L20-1) | AB21: =IF($A21="","",$AB20*(1+$Z21)) | AC21: =IF($A21="","",MAX($AB$4:$AB21)) | AD21: =IF($A21="","",$AB21/$AC21-1) | AE21: =IF($A21="","",$AE20*(1+$AA21))
M22: =IF($A22="",0,SUMIFS(Trades!$I$4:$I$40,Trades!$D$4:$D$40,B$3,Trades!$B$4:$B$40,"<="&$A22)) -> 0 | N22: =IF($A22="",0,SUMIFS(Trades!$I$4:$I$40,Trades!$D$4:$D$40,C$3,Trades!$B$4:$B$40,"<="&$A22)) -> 0 | O22: =IF($A22="",0,SUMIFS(Trades!$I$4:$I$40,Trades!$D$4:$D$40,D$3,Trades!$B$4:$B$40,"<="&$A22)) -> 0 | P22: =IF($A22="",0,SUMIFS(Trades!$I$4:$I$40,Trades!$D$4:$D$40,E$3,Trades!$B$4:$B$40,"<="&$A22)) -> 0 | Q22: =IF($A22="",0,SUMIFS(Trades!$I$4:$I$40,Trades!$D$4:$D$40,F$3,Trades!$B$4:$B$40,"<="&$A22)) -> 0 | R22: =IF($A22="",0,SUMIFS(Trades!$I$4:$I$40,Trades!$D$4:$D$40,G$3,Trades!$B$4:$B$40,"<="&$A22)) -> 0 | S22: =IF($A22="",0,SUMIFS(Trades!$I$4:$I$40,Trades!$D$4:$D$40,H$3,Trades!$B$4:$B$40,"<="&$A22)) -> 0 | T22: =IF($A22="",0,SUMIFS(Trades!$I$4:$I$40,Trades!$D$4:$D$40,I$3,Trades!$B$4:$B$40,"<="&$A22)) -> 0 | ... V22: =IF($A22="",0,SUMIFS(Trades!$I$4:$I$40,Trades!$D$4:$D$40,K$3,Trades!$B$4:$B$40,"<="&$A22)) -> 0 | W22: =IF($A22="",0,Settings!$B$4+SUMIFS(CashEvents!$E$4:$E$30,CashEvents!$A$4:$A$30,"<="&$A22)+SUMIFS(Trades!$J$4:$J$40,Trades!$B$4:$B$40,"<="&$A22)) -> 0 | X22: =IF($A22="","",SUMPRODUCT($B22:$K22,$M22:$V22)+$W22) | Y22: =IF(OR($A22="",$A21=""),"",SUMIFS(CashEvents!$E$4:$E$30,CashEvents!$A$4:$A$30,">"&$A21,CashEvents!$A$4:$A$30,"<="&$A22)) | Z22: =IF(OR($A22="",$A21=""),"",($X22-$Y22)/$X21-1) | AA22: =IF(OR($A22="",$L22="",$L21=""),"",$L22/$L21-1) | AB22: =IF($A22="","",$AB21*(1+$Z22)) | AC22: =IF($A22="","",MAX($AB$4:$AB22)) | AD22: =IF($A22="","",$AB22/$AC22-1) | AE22: =IF($A22="","",$AE21*(1+$AA22))
... M40: =IF($A40="",0,SUMIFS(Trades!$I$4:$I$40,Trades!$D$4:$D$40,B$3,Trades!$B$4:$B$40,"<="&$A40)) -> 0 | N40: =IF($A40="",0,SUMIFS(Trades!$I$4:$I$40,Trades!$D$4:$D$40,C$3,Trades!$B$4:$B$40,"<="&$A40)) -> 0 | O40: =IF($A40="",0,SUMIFS(Trades!$I$4:$I$40,Trades!$D$4:$D$40,D$3,Trades!$B$4:$B$40,"<="&$A40)) -> 0 | P40: =IF($A40="",0,SUMIFS(Trades!$I$4:$I$40,Trades!$D$4:$D$40,E$3,Trades!$B$4:$B$40,"<="&$A40)) -> 0 | Q40: =IF($A40="",0,SUMIFS(Trades!$I$4:$I$40,Trades!$D$4:$D$40,F$3,Trades!$B$4:$B$40,"<="&$A40)) -> 0 | R40: =IF($A40="",0,SUMIFS(Trades!$I$4:$I$40,Trades!$D$4:$D$40,G$3,Trades!$B$4:$B$40,"<="&$A40)) -> 0 | S40: =IF($A40="",0,SUMIFS(Trades!$I$4:$I$40,Trades!$D$4:$D$40,H$3,Trades!$B$4:$B$40,"<="&$A40)) -> 0 | T40: =IF($A40="",0,SUMIFS(Trades!$I$4:$I$40,Trades!$D$4:$D$40,I$3,Trades!$B$4:$B$40,"<="&$A40)) -> 0 | ... V40: =IF($A40="",0,SUMIFS(Trades!$I$4:$I$40,Trades!$D$4:$D$40,K$3,Trades!$B$4:$B$40,"<="&$A40)) -> 0 | W40: =IF($A40="",0,Settings!$B$4+SUMIFS(CashEvents!$E$4:$E$30,CashEvents!$A$4:$A$30,"<="&$A40)+SUMIFS(Trades!$J$4:$J$40,Trades!$B$4:$B$40,"<="&$A40)) -> 0 | X40: =IF($A40="","",SUMPRODUCT($B40:$K40,$M40:$V40)+$W40) | Y40: =IF(OR($A40="",$A39=""),"",SUMIFS(CashEvents!$E$4:$E$30,CashEvents!$A$4:$A$30,">"&$A39,CashEvents!$A$4:$A$30,"<="&$A40)) | Z40: =IF(OR($A40="",$A39=""),"",($X40-$Y40)/$X39-1) | AA40: =IF(OR($A40="",$L40="",$L39=""),"",$L40/$L39-1) | AB40: =IF($A40="","",$AB39*(1+$Z40)) | AC40: =IF($A40="","",MAX($AB$4:$AB40)) | AD40: =IF($A40="","",$AB40/$AC40-1) | AE40: =IF($A40="","",$AE39*(1+$AA40))

Sheet Dashboard
A1: Dashboard — account & holdings
A2: All calculated. Mirrors the app Dashboard (Trading 212-style figures).
A4: Portfolio value ($) | B4: =$E$25+$B$5 -> 28846
A5: Free funds / cash ($) | B5: =Settings!$B$4+SUM(CashEvents!$E$4:$E$30)+SUM(Trades!$J$4:$J$40) -> 13590
A6: Invested — cost basis ($) | B6: =$F$25 -> 14260
A7: Unrealized P/L ($) | B7: =$E$25-$F$25 -> 996
A8: Realized P/L ($) | B8: =SUM(Trades!$L$4:$L$40) -> -150
A9: Net deposits ($) | B9: =Settings!$B$4+SUM(CashEvents!$E$4:$E$30) -> 28000
A10: Total return ($) | B10: =$B$4-$B$9 -> 846
A11: Total return (%) | B11: =IFERROR($B$10/$B$9,"") -> 0.030214286
A12: All decisions vs doing nothing ($) | B12: =SUM(Decisions!$L$4:$L$20) -> 846
A14: Ticker | B14: Shares | C14: Avg cost ($) | D14: Price ($) | E14: Value ($) | F14: Cost basis ($) | G14: Unrealized P/L ($) | H14: Weight (incl cash) | I14: Sector
A15: VOO | B15: =IF($A15="","",SUMIFS(Trades!$I$4:$I$40,Trades!$D$4:$D$40,$A15)) -> 20 | C15: =IF($A15="","",IFERROR(SUMPRODUCT((Trades!$D$4:$D$40=$A15)*(Trades!$E$4:$E$40="Buy")*(Trades!$F$4:$F$40*Trades!$G$4:$G$40+Trades!$H$4:$H$40))/SUMPRODUCT((Trades!$D$4:$D$40=$A15)*(Trades!$E$4:$E$40="Buy")*Trades!$F$4:$F$40),0)) -> 480 | D15: =IF($A15="","",SUMIFS(Prices!$B$4:$B$13,Prices!$A$4:$A$13,$A15)) -> 510 | E15: =IF($A15="","",$B15*$D15) -> 10200 | F15: =IF($A15="","",$B15*$C15) -> 9600 | G15: =IF($A15="","",$E15-$F15) -> 600 | H15: =IF($A15="","",IFERROR($E15/$B$4,"")) -> 0.35360189 | I15: =IF($A15="","",IFERROR(INDEX(Prices!$C$4:$C$13,MATCH($A15,Prices!$A$4:$A$13,0)),"")) -> ETF / Fund
A16: AAPL | B16: =IF($A16="","",SUMIFS(Trades!$I$4:$I$40,Trades!$D$4:$D$40,$A16)) -> 10 | C16: =IF($A16="","",IFERROR(SUMPRODUCT((Trades!$D$4:$D$40=$A16)*(Trades!$E$4:$E$40="Buy")*(Trades!$F$4:$F$40*Trades!$G$4:$G$40+Trades!$H$4:$H$40))/SUMPRODUCT((Trades!$D$4:$D$40=$A16)*(Trades!$E$4:$E$40="Buy")*Trades!$F$4:$F$40),0)) -> 220 | D16: =IF($A16="","",SUMIFS(Prices!$B$4:$B$13,Prices!$A$4:$A$13,$A16)) -> 235 | E16: =IF($A16="","",$B16*$D16) -> 2350 | F16: =IF($A16="","",$B16*$C16) -> 2200 | G16: =IF($A16="","",$E16-$F16) -> 150 | H16: =IF($A16="","",IFERROR($E16/$B$4,"")) -> 0.081467101 | I16: =IF($A16="","",IFERROR(INDEX(Prices!$C$4:$C$13,MATCH($A16,Prices!$A$4:$A$13,0)),"")) -> Technology
A17: NVDA | B17: =IF($A17="","",SUMIFS(Trades!$I$4:$I$40,Trades!$D$4:$D$40,$A17)) -> 10 | C17: =IF($A17="","",IFERROR(SUMPRODUCT((Trades!$D$4:$D$40=$A17)*(Trades!$E$4:$E$40="Buy")*(Trades!$F$4:$F$40*Trades!$G$4:$G$40+Trades!$H$4:$H$40))/SUMPRODUCT((Trades!$D$4:$D$40=$A17)*(Trades!$E$4:$E$40="Buy")*Trades!$F$4:$F$40),0)) -> 120 | D17: =IF($A17="","",SUMIFS(Prices!$B$4:$B$13,Prices!$A$4:$A$13,$A17)) -> 141 | E17: =IF($A17="","",$B17*$D17) -> 1410 | F17: =IF($A17="","",$B17*$C17) -> 1200 | G17: =IF($A17="","",$E17-$F17) -> 210 | H17: =IF($A17="","",IFERROR($E17/$B$4,"")) -> 0.048880261 | I17: =IF($A17="","",IFERROR(INDEX(Prices!$C$4:$C$13,MATCH($A17,Prices!$A$4:$A$13,0)),"")) -> Semiconductors
A18: MSFT | B18: =IF($A18="","",SUMIFS(Trades!$I$4:$I$40,Trades!$D$4:$D$40,$A18)) -> 3 | C18: =IF($A18="","",IFERROR(SUMPRODUCT((Trades!$D$4:$D$40=$A18)*(Trades!$E$4:$E$40="Buy")*(Trades!$F$4:$F$40*Trades!$G$4:$G$40+Trades!$H$4:$H$40))/SUMPRODUCT((Trades!$D$4:$D$40=$A18)*(Trades!$E$4:$E$40="Buy")*Trades!$F$4:$F$40),0)) -> 420 | D18: =IF($A18="","",SUMIFS(Prices!$B$4:$B$13,Prices!$A$4:$A$13,$A18)) -> 432 | E18: =IF($A18="","",$B18*$D18) -> 1296 | F18: =IF($A18="","",$B18*$C18) -> 1260 | G18: =IF($A18="","",$E18-$F18) -> 36 | H18: =IF($A18="","",IFERROR($E18/$B$4,"")) -> 0.04492824 | I18: =IF($A18="","",IFERROR(INDEX(Prices!$C$4:$C$13,MATCH($A18,Prices!$A$4:$A$13,0)),"")) -> Software
A19: INTC | B19: =IF($A19="","",SUMIFS(Trades!$I$4:$I$40,Trades!$D$4:$D$40,$A19)) -> 0 | C19: =IF($A19="","",IFERROR(SUMPRODUCT((Trades!$D$4:$D$40=$A19)*(Trades!$E$4:$E$40="Buy")*(Trades!$F$4:$F$40*Trades!$G$4:$G$40+Trades!$H$4:$H$40))/SUMPRODUCT((Trades!$D$4:$D$40=$A19)*(Trades!$E$4:$E$40="Buy")*Trades!$F$4:$F$40),0)) -> 35 | D19: =IF($A19="","",SUMIFS(Prices!$B$4:$B$13,Prices!$A$4:$A$13,$A19)) -> 24 | E19: =IF($A19="","",$B19*$D19) -> 0 | F19: =IF($A19="","",$B19*$C19) -> 0 | G19: =IF($A19="","",$E19-$F19) -> 0 | H19: =IF($A19="","",IFERROR($E19/$B$4,"")) -> 0 | I19: =IF($A19="","",IFERROR(INDEX(Prices!$C$4:$C$13,MATCH($A19,Prices!$A$4:$A$13,0)),"")) -> Semiconductors
B20: =IF($A20="","",SUMIFS(Trades!$I$4:$I$40,Trades!$D$4:$D$40,$A20)) | C20: =IF($A20="","",IFERROR(SUMPRODUCT((Trades!$D$4:$D$40=$A20)*(Trades!$E$4:$E$40="Buy")*(Trades!$F$4:$F$40*Trades!$G$4:$G$40+Trades!$H$4:$H$40))/SUMPRODUCT((Trades!$D$4:$D$40=$A20)*(Trades!$E$4:$E$40="Buy")*Trades!$F$4:$F$40),0)) | D20: =IF($A20="","",SUMIFS(Prices!$B$4:$B$13,Prices!$A$4:$A$13,$A20)) | E20: =IF($A20="","",$B20*$D20) | F20: =IF($A20="","",$B20*$C20) | G20: =IF($A20="","",$E20-$F20) | H20: =IF($A20="","",IFERROR($E20/$B$4,"")) | I20: =IF($A20="","",IFERROR(INDEX(Prices!$C$4:$C$13,MATCH($A20,Prices!$A$4:$A$13,0)),""))
B21: =IF($A21="","",SUMIFS(Trades!$I$4:$I$40,Trades!$D$4:$D$40,$A21)) | C21: =IF($A21="","",IFERROR(SUMPRODUCT((Trades!$D$4:$D$40=$A21)*(Trades!$E$4:$E$40="Buy")*(Trades!$F$4:$F$40*Trades!$G$4:$G$40+Trades!$H$4:$H$40))/SUMPRODUCT((Trades!$D$4:$D$40=$A21)*(Trades!$E$4:$E$40="Buy")*Trades!$F$4:$F$40),0)) | D21: =IF($A21="","",SUMIFS(Prices!$B$4:$B$13,Prices!$A$4:$A$13,$A21)) | E21: =IF($A21="","",$B21*$D21) | F21: =IF($A21="","",$B21*$C21) | G21: =IF($A21="","",$E21-$F21) | H21: =IF($A21="","",IFERROR($E21/$B$4,"")) | I21: =IF($A21="","",IFERROR(INDEX(Prices!$C$4:$C$13,MATCH($A21,Prices!$A$4:$A$13,0)),""))
B22: =IF($A22="","",SUMIFS(Trades!$I$4:$I$40,Trades!$D$4:$D$40,$A22)) | C22: =IF($A22="","",IFERROR(SUMPRODUCT((Trades!$D$4:$D$40=$A22)*(Trades!$E$4:$E$40="Buy")*(Trades!$F$4:$F$40*Trades!$G$4:$G$40+Trades!$H$4:$H$40))/SUMPRODUCT((Trades!$D$4:$D$40=$A22)*(Trades!$E$4:$E$40="Buy")*Trades!$F$4:$F$40),0)) | D22: =IF($A22="","",SUMIFS(Prices!$B$4:$B$13,Prices!$A$4:$A$13,$A22)) | E22: =IF($A22="","",$B22*$D22) | F22: =IF($A22="","",$B22*$C22) | G22: =IF($A22="","",$E22-$F22) | H22: =IF($A22="","",IFERROR($E22/$B$4,"")) | I22: =IF($A22="","",IFERROR(INDEX(Prices!$C$4:$C$13,MATCH($A22,Prices!$A$4:$A$13,0)),""))
B23: =IF($A23="","",SUMIFS(Trades!$I$4:$I$40,Trades!$D$4:$D$40,$A23)) | C23: =IF($A23="","",IFERROR(SUMPRODUCT((Trades!$D$4:$D$40=$A23)*(Trades!$E$4:$E$40="Buy")*(Trades!$F$4:$F$40*Trades!$G$4:$G$40+Trades!$H$4:$H$40))/SUMPRODUCT((Trades!$D$4:$D$40=$A23)*(Trades!$E$4:$E$40="Buy")*Trades!$F$4:$F$40),0)) | D23: =IF($A23="","",SUMIFS(Prices!$B$4:$B$13,Prices!$A$4:$A$13,$A23)) | E23: =IF($A23="","",$B23*$D23) | F23: =IF($A23="","",$B23*$C23) | G23: =IF($A23="","",$E23-$F23) | H23: =IF($A23="","",IFERROR($E23/$B$4,"")) | I23: =IF($A23="","",IFERROR(INDEX(Prices!$C$4:$C$13,MATCH($A23,Prices!$A$4:$A$13,0)),""))
B24: =IF($A24="","",SUMIFS(Trades!$I$4:$I$40,Trades!$D$4:$D$40,$A24)) | C24: =IF($A24="","",IFERROR(SUMPRODUCT((Trades!$D$4:$D$40=$A24)*(Trades!$E$4:$E$40="Buy")*(Trades!$F$4:$F$40*Trades!$G$4:$G$40+Trades!$H$4:$H$40))/SUMPRODUCT((Trades!$D$4:$D$40=$A24)*(Trades!$E$4:$E$40="Buy")*Trades!$F$4:$F$40),0)) | D24: =IF($A24="","",SUMIFS(Prices!$B$4:$B$13,Prices!$A$4:$A$13,$A24)) | E24: =IF($A24="","",$B24*$D24) | F24: =IF($A24="","",$B24*$C24) | G24: =IF($A24="","",$E24-$F24) | H24: =IF($A24="","",IFERROR($E24/$B$4,"")) | I24: =IF($A24="","",IFERROR(INDEX(Prices!$C$4:$C$13,MATCH($A24,Prices!$A$4:$A$13,0)),""))
A25: Securities total | E25: =SUM(E15:E24) -> 15256 | F25: =SUM(F15:F24) -> 14260
A26: Cash | E26: =$B$5 -> 13590 | H26: =IFERROR($B$5/$B$4,"") -> 0.47112251

Sheet XRay
A1: X-Ray — risk statistics, concentration, composition
A2: Same math as the app: flow-adjusted time-weighted returns per snapshot interval, annualized by observed frequency.
A3: RISK STATISTICS (vs benchmark)
A4: Observations (intervals) | B4: =COUNT(Snapshots!$Z$5:$Z$40) -> 6 | C4: Snapshot-to-snapshot returns available.
A5: Snapshots | B5: =COUNT(Snapshots!$A$4:$A$40) -> 7
A6: Span (days) | B6: =IF($B$4=0,"",INDEX(Snapshots!$A$4:$A$40,$B$5)-Snapshots!$A$4) -> 74 | C6: First to last snapshot.
A7: Observations per year | B7: =IF($B$4=0,"",$B$4/($B$6/365.25)) -> 29.614865 | C7: Annualization frequency.
A8: Mean return / interval | B8: =IF($B$4=0,"",AVERAGE(OFFSET(Snapshots!$Z$5,0,0,$B$4,1))) -> 0.0048987254
A9: Std dev / interval | B9: =IF($B$4<2,"",STDEV(OFFSET(Snapshots!$Z$5,0,0,$B$4,1))) -> 0.0034605029
A10: Annualized return (TWR) | B10: =IF($B$4=0,"",INDEX(Snapshots!$AB$4:$AB$40,$B$5)^(365.25/$B$6)-1) -> 0.1555478 | C10: CAGR of the chained index — deposits excluded.
A11: Annualized volatility | B11: =IF($B$9="","",$B$9*SQRT($B$7)) -> 0.018831898 | C11: Std dev × √(obs/year).
A12: Sharpe ratio | B12: =IF(OR($B$9="",$B$9=0),"",($B$8-Settings!$B$6/$B$7)/$B$9*SQRT($B$7)) -> 5.5796336 | C12: Excess return per unit of risk.
A13: Max drawdown | B13: =IF($B$4=0,"",MIN(Snapshots!$AD$5:$AD$40)) -> -0.00039793076 | C13: Worst peak-to-trough of the TWR index.
A14: Beta | B14: =IF($B$4<2,"",IFERROR(SLOPE(OFFSET(Snapshots!$Z$5,0,0,$B$4,1),OFFSET(Snapshots!$AA$5,0,0,$B$4,1)),"")) -> 0.73961075 | C14: Regression slope vs benchmark returns.
A15: R² | B15: =IF($B$4<2,"",IFERROR(RSQ(OFFSET(Snapshots!$Z$5,0,0,$B$4,1),OFFSET(Snapshots!$AA$5,0,0,$B$4,1)),"")) -> 0.50590935 | C15: Share of moves explained by the benchmark.
A16: Benchmark annualized return | B16: =IF($B$4=0,"",INDEX(Snapshots!$AE$4:$AE$40,$B$5)^(365.25/$B$6)-1) -> 0.27910155
A17: Alpha (Jensen, annualized) | B17: =IF(OR($B$14="",$B$16=""),"",$B$10-(Settings!$B$6+$B$14*($B$16-Settings!$B$6))) -> -0.061294279 | C17: Return above CAPM expectation.
A19: CONCENTRATION
A20: Positions | B20: =COUNTIF(Dashboard!$E$15:$E$24,">0.000001") -> 4
A21: Effective holdings (1/Herfindahl) | B21: =IFERROR(1/SUMSQ($E$28:$E$37),"") -> 2.0555073
A22: Largest position (weight) | B22: =IFERROR(MAX($E$28:$E$37),"") -> 0.66858941
A23: Top 3 combined (weight) | B23: =IFERROR(LARGE($E$28:$E$37,1),0)+IFERROR(LARGE($E$28:$E$37,2),0)+IFERROR(LARGE($E$28:$E$37,3),0) -> 0.91504982
D27: Ticker | E27: Weight (securities only)
D28: =IF(Dashboard!$A15="","",Dashboard!$A15) -> VOO | E28: =IF(Dashboard!$A15="","",IFERROR(Dashboard!$E15/Dashboard!$E$25,"")) -> 0.66858941
D29: =IF(Dashboard!$A16="","",Dashboard!$A16) -> AAPL | E29: =IF(Dashboard!$A16="","",IFERROR(Dashboard!$E16/Dashboard!$E$25,"")) -> 0.15403776
D30: =IF(Dashboard!$A17="","",Dashboard!$A17) -> NVDA | E30: =IF(Dashboard!$A17="","",IFERROR(Dashboard!$E17/Dashboard!$E$25,"")) -> 0.092422653
D31: =IF(Dashboard!$A18="","",Dashboard!$A18) -> MSFT | E31: =IF(Dashboard!$A18="","",IFERROR(Dashboard!$E18/Dashboard!$E$25,"")) -> 0.084950184
D32: =IF(Dashboard!$A19="","",Dashboard!$A19) -> INTC | E32: =IF(Dashboard!$A19="","",IFERROR(Dashboard!$E19/Dashboard!$E$25,"")) -> 0
D33: =IF(Dashboard!$A20="","",Dashboard!$A20) | E33: =IF(Dashboard!$A20="","",IFERROR(Dashboard!$E20/Dashboard!$E$25,""))
D34: =IF(Dashboard!$A21="","",Dashboard!$A21) | E34: =IF(Dashboard!$A21="","",IFERROR(Dashboard!$E21/Dashboard!$E$25,""))
D35: =IF(Dashboard!$A22="","",Dashboard!$A22) | E35: =IF(Dashboard!$A22="","",IFERROR(Dashboard!$E22/Dashboard!$E$25,""))
D36: =IF(Dashboard!$A23="","",Dashboard!$A23) | E36: =IF(Dashboard!$A23="","",IFERROR(Dashboard!$E23/Dashboard!$E$25,""))
D37: =IF(Dashboard!$A24="","",Dashboard!$A24) | E37: =IF(Dashboard!$A24="","",IFERROR(Dashboard!$E24/Dashboard!$E$25,""))
A39: SECTORS (weight among securities)
A40: Sector | B40: Value ($) | C40: Weight
A41: ETF / Fund | B41: =IF($A41="","",SUMIFS(Dashboard!$E$15:$E$24,Dashboard!$I$15:$I$24,$A41)) -> 10200 | C41: =IF($A41="","",IFERROR($B41/Dashboard!$E$25,"")) -> 0.66858941
A42: Technology | B42: =IF($A42="","",SUMIFS(Dashboard!$E$15:$E$24,Dashboard!$I$15:$I$24,$A42)) -> 2350 | C42: =IF($A42="","",IFERROR($B42/Dashboard!$E$25,"")) -> 0.15403776
A43: Semiconductors | B43: =IF($A43="","",SUMIFS(Dashboard!$E$15:$E$24,Dashboard!$I$15:$I$24,$A43)) -> 1410 | C43: =IF($A43="","",IFERROR($B43/Dashboard!$E$25,"")) -> 0.092422653
A44: Software | B44: =IF($A44="","",SUMIFS(Dashboard!$E$15:$E$24,Dashboard!$I$15:$I$24,$A44)) -> 1296 | C44: =IF($A44="","",IFERROR($B44/Dashboard!$E$25,"")) -> 0.084950184
B45: =IF($A45="","",SUMIFS(Dashboard!$E$15:$E$24,Dashboard!$I$15:$I$24,$A45)) | C45: =IF($A45="","",IFERROR($B45/Dashboard!$E$25,""))
B46: =IF($A46="","",SUMIFS(Dashboard!$E$15:$E$24,Dashboard!$I$15:$I$24,$A46)) | C46: =IF($A46="","",IFERROR($B46/Dashboard!$E$25,""))
B47: =IF($A47="","",SUMIFS(Dashboard!$E$15:$E$24,Dashboard!$I$15:$I$24,$A47)) | C47: =IF($A47="","",IFERROR($B47/Dashboard!$E$25,""))
B48: =IF($A48="","",SUMIFS(Dashboard!$E$15:$E$24,Dashboard!$I$15:$I$24,$A48)) | C48: =IF($A48="","",IFERROR($B48/Dashboard!$E$25,""))
A50: Tag each ticker's sector on the Prices sheet; add sector names here (blue) as needed.

Sheet Reconciliation
A1: Reconciliation — this workbook vs the app
A2: Column C: values shown by the app with the same demo data (read from the app UI, 2026-07-01 — display-rounded). Column D: this workbook's live formulas. Every Status must read PASS.
A4: Metric | B4: App screen | C4: App shows | D4: Workbook computes | E4: Difference | F4: Tolerance | G4: Status
A5: Portfolio value | B5: Dashboard | C5: 28846 | D5: =Dashboard!$B$4 -> 28846 | E5: =IF(OR($C5="",$D5=""),"",$D5-$C5) -> 0 | F5: 1 | G5: =IF($E5="","",IF(ABS($E5)<=$F5,"PASS","CHECK")) -> PASS
A6: Free funds (cash) | B6: Dashboard | C6: 13590 | D6: =Dashboard!$B$5 -> 13590 | E6: =IF(OR($C6="",$D6=""),"",$D6-$C6) -> 0 | F6: 1 | G6: =IF($E6="","",IF(ABS($E6)<=$F6,"PASS","CHECK")) -> PASS
A7: Invested (cost basis) | B7: Dashboard | C7: 14260 | D7: =Dashboard!$B$6 -> 14260 | E7: =IF(OR($C7="",$D7=""),"",$D7-$C7) -> 0 | F7: 1 | G7: =IF($E7="","",IF(ABS($E7)<=$F7,"PASS","CHECK")) -> PASS
A8: Unrealized P/L | B8: Dashboard | C8: 996 | D8: =Dashboard!$B$7 -> 996 | E8: =IF(OR($C8="",$D8=""),"",$D8-$C8) -> 0 | F8: 1 | G8: =IF($E8="","",IF(ABS($E8)<=$F8,"PASS","CHECK")) -> PASS
A9: Realized P/L | B9: Dashboard | C9: -150 | D9: =Dashboard!$B$8 -> -150 | E9: =IF(OR($C9="",$D9=""),"",$D9-$C9) -> 0 | F9: 1 | G9: =IF($E9="","",IF(ABS($E9)<=$F9,"PASS","CHECK")) -> PASS
A10: Net deposits | B10: Dashboard | C10: 28000 | D10: =Dashboard!$B$9 -> 28000 | E10: =IF(OR($C10="",$D10=""),"",$D10-$C10) -> 0 | F10: 1 | G10: =IF($E10="","",IF(ABS($E10)<=$F10,"PASS","CHECK")) -> PASS
A11: Total return ($) | B11: Dashboard | C11: 846 | D11: =Dashboard!$B$10 -> 846 | E11: =IF(OR($C11="",$D11=""),"",$D11-$C11) -> 0 | F11: 1 | G11: =IF($E11="","",IF(ABS($E11)<=$F11,"PASS","CHECK")) -> PASS
A12: Total return (%) | B12: Dashboard | C12: 0.03 | D12: =Dashboard!$B$11 -> 0.030214286 | E12: =IF(OR($C12="",$D12=""),"",$D12-$C12) -> 0.00021428571 | F12: 0.0015 | G12: =IF($E12="","",IF(ABS($E12)<=$F12,"PASS","CHECK")) -> PASS
A13: All decisions vs doing nothing | B13: Dashboard | C13: 846 | D13: =Dashboard!$B$12 -> 846 | E13: =IF(OR($C13="",$D13=""),"",$D13-$C13) -> 0 | F13: 1 | G13: =IF($E13="","",IF(ABS($E13)<=$F13,"PASS","CHECK")) -> PASS
A14: D-001 vs doing nothing (%) | B14: Decisions list | C14: 0.015 | D14: =Decisions!$M$4 -> 0.0154 | E14: =IF(OR($C14="",$D14=""),"",$D14-$C14) -> 0.0004 | F14: 0.0015 | G14: =IF($E14="","",IF(ABS($E14)<=$F14,"PASS","CHECK")) -> PASS
A15: D-002 decision value ($) | B15: Decision detail | C15: 450 | D15: =Decisions!$L$5 -> 450 | E15: =IF(OR($C15="",$D15=""),"",$D15-$C15) -> 0 | F15: 1 | G15: =IF($E15="","",IF(ABS($E15)<=$F15,"PASS","CHECK")) -> PASS
A16: D-002 vs doing nothing (%) | B16: Decisions list | C16: 0.018 | D16: =Decisions!$M$5 -> 0.017727004 | E16: =IF(OR($C16="",$D16=""),"",$D16-$C16) -> -0.00027299586 | F16: 0.0015 | G16: =IF($E16="","",IF(ABS($E16)<=$F16,"PASS","CHECK")) -> PASS
A17: D-003 vs doing nothing (%) | B17: Decisions list | C17: 0 | D17: =Decisions!$M$6 -> 0.00038148084 | E17: =IF(OR($C17="",$D17=""),"",$D17-$C17) -> 0.00038148084 | F17: 0.0015 | G17: =IF($E17="","",IF(ABS($E17)<=$F17,"PASS","CHECK")) -> PASS
A18: Allocation — VOO | B18: Allocation donut | C18: 0.354 | D18: =Dashboard!$H$15 -> 0.35360189 | E18: =IF(OR($C18="",$D18=""),"",$D18-$C18) -> -0.00039811412 | F18: 0.0015 | G18: =IF($E18="","",IF(ABS($E18)<=$F18,"PASS","CHECK")) -> PASS
A19: Allocation — AAPL | B19: Allocation donut | C19: 0.081 | D19: =Dashboard!$H$16 -> 0.081467101 | E19: =IF(OR($C19="",$D19=""),"",$D19-$C19) -> 0.00046710116 | F19: 0.0015 | G19: =IF($E19="","",IF(ABS($E19)<=$F19,"PASS","CHECK")) -> PASS
A20: Allocation — NVDA | B20: Allocation donut | C20: 0.049 | D20: =Dashboard!$H$17 -> 0.048880261 | E20: =IF(OR($C20="",$D20=""),"",$D20-$C20) -> -0.00011973931 | F20: 0.0015 | G20: =IF($E20="","",IF(ABS($E20)<=$F20,"PASS","CHECK")) -> PASS
A21: Allocation — MSFT | B21: Allocation donut | C21: 0.045 | D21: =Dashboard!$H$18 -> 0.04492824 | E21: =IF(OR($C21="",$D21=""),"",$D21-$C21) -> -7.1760383e-05 | F21: 0.0015 | G21: =IF($E21="","",IF(ABS($E21)<=$F21,"PASS","CHECK")) -> PASS
A22: Allocation — Cash | B22: Allocation donut | C22: 0.471 | D22: =Dashboard!$H$26 -> 0.47112251 | E22: =IF(OR($C22="",$D22=""),"",$D22-$C22) -> 0.00012251265 | F22: 0.0015 | G22: =IF($E22="","",IF(ABS($E22)<=$F22,"PASS","CHECK")) -> PASS
A23: Sharpe ratio | B23: X-Ray | C23: 5.58 | D23: =XRay!$B$12 -> 5.5796336 | E23: =IF(OR($C23="",$D23=""),"",$D23-$C23) -> -0.00036637409 | F23: 0.05 | G23: =IF($E23="","",IF(ABS($E23)<=$F23,"PASS","CHECK")) -> PASS
A24: Beta | B24: X-Ray | C24: 0.74 | D24: =XRay!$B$14 -> 0.73961075 | E24: =IF(OR($C24="",$D24=""),"",$D24-$C24) -> -0.00038924651 | F24: 0.02 | G24: =IF($E24="","",IF(ABS($E24)<=$F24,"PASS","CHECK")) -> PASS
A25: Alpha (annualized) | B25: X-Ray | C25: -0.061 | D25: =XRay!$B$17 -> -0.061294279 | E25: =IF(OR($C25="",$D25=""),"",$D25-$C25) -> -0.00029427911 | F25: 0.005 | G25: =IF($E25="","",IF(ABS($E25)<=$F25,"PASS","CHECK")) -> PASS
A26: Volatility (annualized) | B26: X-Ray | C26: 0.019 | D26: =XRay!$B$11 -> 0.018831898 | E26: =IF(OR($C26="",$D26=""),"",$D26-$C26) -> -0.0001681021 | F26: 0.0015 | G26: =IF($E26="","",IF(ABS($E26)<=$F26,"PASS","CHECK")) -> PASS
A27: Max drawdown | B27: X-Ray | C27: 0 | D27: =XRay!$B$13 -> -0.00039793076 | E27: =IF(OR($C27="",$D27=""),"",$D27-$C27) -> -0.00039793076 | F27: 0.001 | G27: =IF($E27="","",IF(ABS($E27)<=$F27,"PASS","CHECK")) -> PASS
A28: R² | B28: X-Ray | C28: 0.51 | D28: =XRay!$B$15 -> 0.50590935 | E28: =IF(OR($C28="",$D28=""),"",$D28-$C28) -> -0.0040906533 | F28: 0.01 | G28: =IF($E28="","",IF(ABS($E28)<=$F28,"PASS","CHECK")) -> PASS
A29: Annualized return (TWR) | B29: X-Ray | C29: 0.156 | D29: =XRay!$B$10 -> 0.1555478 | E29: =IF(OR($C29="",$D29=""),"",$D29-$C29) -> -0.00045220113 | F29: 0.002 | G29: =IF($E29="","",IF(ABS($E29)<=$F29,"PASS","CHECK")) -> PASS
A30: Benchmark annualized return | B30: X-Ray | C30: 0.279 | D30: =XRay!$B$16 -> 0.27910155 | E30: =IF(OR($C30="",$D30=""),"",$D30-$C30) -> 0.00010155058 | F30: 0.002 | G30: =IF($E30="","",IF(ABS($E30)<=$F30,"PASS","CHECK")) -> PASS
A31: Positions | B31: X-Ray | C31: 4 | D31: =XRay!$B$20 -> 4 | E31: =IF(OR($C31="",$D31=""),"",$D31-$C31) -> 0 | F31: 0.1 | G31: =IF($E31="","",IF(ABS($E31)<=$F31,"PASS","CHECK")) -> PASS
A32: Effective holdings | B32: X-Ray | C32: 2.1 | D32: =XRay!$B$21 -> 2.0555073 | E32: =IF(OR($C32="",$D32=""),"",$D32-$C32) -> -0.044492696 | F32: 0.05 | G32: =IF($E32="","",IF(ABS($E32)<=$F32,"PASS","CHECK")) -> PASS
A33: Largest position | B33: X-Ray | C33: 0.669 | D33: =XRay!$B$22 -> 0.66858941 | E33: =IF(OR($C33="",$D33=""),"",$D33-$C33) -> -0.00041059255 | F33: 0.0015 | G33: =IF($E33="","",IF(ABS($E33)<=$F33,"PASS","CHECK")) -> PASS
A34: Top 3 combined | B34: X-Ray | C34: 0.915 | D34: =XRay!$B$23 -> 0.91504982 | E34: =IF(OR($C34="",$D34=""),"",$D34-$C34) -> 4.9816466e-05 | F34: 0.0015 | G34: =IF($E34="","",IF(ABS($E34)<=$F34,"PASS","CHECK")) -> PASS
A35: Sector — ETF / Fund | B35: X-Ray | C35: 0.669 | D35: =XRay!$C$41 -> 0.66858941 | E35: =IF(OR($C35="",$D35=""),"",$D35-$C35) -> -0.00041059255 | F35: 0.0015 | G35: =IF($E35="","",IF(ABS($E35)<=$F35,"PASS","CHECK")) -> PASS
A36: Sector — Technology | B36: X-Ray | C36: 0.154 | D36: =XRay!$C$42 -> 0.15403776 | E36: =IF(OR($C36="",$D36=""),"",$D36-$C36) -> 3.7755637e-05 | F36: 0.0015 | G36: =IF($E36="","",IF(ABS($E36)<=$F36,"PASS","CHECK")) -> PASS
A37: Sector — Semiconductors | B37: X-Ray | C37: 0.092 | D37: =XRay!$C$43 -> 0.092422653 | E37: =IF(OR($C37="",$D37=""),"",$D37-$C37) -> 0.00042265338 | F37: 0.0015 | G37: =IF($E37="","",IF(ABS($E37)<=$F37,"PASS","CHECK")) -> PASS
A38: Sector — Software | B38: X-Ray | C38: 0.085 | D38: =XRay!$C$44 -> 0.084950184 | E38: =IF(OR($C38="",$D38=""),"",$D38-$C38) -> -4.9816466e-05 | F38: 0.0015 | G38: =IF($E38="","",IF(ABS($E38)<=$F38,"PASS","CHECK")) -> PASS
A40: METHOD MAPPING — where each app calculation lives in this workbook
A41: Workbook location | B41: App feature | C41: App source function
A42: Trades + CashEvents + Settings | B42: Ledger: positions, cash, realized P/L, net deposits | C42: replayLedger() in src/lib/portfolio.ts
A43: Dashboard | B43: Dashboard tab: account figures, holdings, weights | C43: portfolioValue(), costBasis()
A44: Decisions J:M | B44: Decision detail: ghost (just before) vs acted (just after), valued at current prices | C44: decisionOutcome()
A45: Snapshots Z:AE | B45: Equity curve + return series: flow-adjusted time-weighted returns per interval | C45: intervalReturns() in src/lib/analytics.ts
A46: XRay risk block | B46: X-Ray: vol = sd×√(obs/yr); Sharpe = (mean−rf/ppy)/sd×√ppy; CAGR from chained index; Beta/R² regression; Jensen alpha | C46: riskStats()
A47: XRay concentration & sectors | B47: X-Ray: Herfindahl effective holdings; sector weights among securities | C47: concentration(), sectorBreakdown()
A49: ASSUMPTIONS & KNOWN DIFFERENCES
A50: 1. App demo dates regenerate relative to "today"; this workbook fixes them to anchor 2026-07-01 with identical day-offsets, so every statistic matches.
A51: 2. "App shows" values were read from the app UI (display-rounded); tolerances cover that rounding only.
A52: 3. Ghost values: the app freezes the ghost snapshot when a decision is created; the workbook recomputes it from the ledger — equivalent for normal decisions. The app's synthetic "Opening portfolio" forces an all-cash ghost; here an opening decision's ghost is starting cash, which is the same thing.
A53: 4. Average cost at sale is exact when buys precede sells per ticker; buying again after a partial sell is approximated (app: sequential weighted average).
A54: 5. Ghost/acted split uses dates (< vs <=); the app uses timestamps — keep one decision per date.
A55: 6. The app collapses price refreshes within 30 minutes into one snapshot; here every Snapshots row is one observation.
